Workbook

Sheet Capa
B3: FORNIX
B4: Base Mestra de Fornecedores — Polo Atacadista do Brás (SP)
B5: Compre direto da fábrica. Sem intermediários. Mais margem no Shopee, Mercado Livre e Instagram.
B7: 1019 | D7: 6
B8: Fornecedores Únicos | D8: Polos / Galerias Mapeados
B11: 22 | D11: 05/08/2026
B12: Categorias de Produto | D12: Atualizado em
B16: Polos incluídos nesta base
B17: Polo / Galeria | F17: Fornecedores
B18: Galeria Pagé | F18: 287
B19: Shopping Total Brás | F19: 255
B20: Shopping Canindé | F20: 193
B21: Shopping Porto Brás | F21: 157
B22: Shopping All Brás | F22: 105
B23: O Melhor do Brás (Diretório) | F23: 22
B24: TOTAL GERAL (base única, sem duplicidades) | F24: =SUM(F18:F23) -> 1019
B27: Como navegar nesta pasta de trabalho
B28: ▸ Base Completa
B29: Todos os 1.0xx fornecedores, filtráveis por polo, categoria e segmento. Use os filtros do cabeçalho.
B30: ▸ Painel por Categoria
B31: Ranking das categorias de produto com mais fornecedores mapeados.
B32: ▸ Painel por Polo
B33: Comparativo do número de fornecedores por shopping/galeria.
B34: ▸ Total Brás / Pagé / Canindé / Porto Brás / All Brás / O Melhor do Brás
B35: Uma aba por polo, já filtrada, pronta para prospecção direcionada.
B36: ▸ Como Usar
B37: Boas práticas de contato, checklist de prospecção e avisos importantes.

Sheet Como Usar
B2: Como usar a base FORNIX
B4: 1. Filtre antes de abordar
B5: Na aba 'Base Completa', use os filtros do cabeçalho (ícone de seta em cada coluna) para cruzar Categoria + Polo e montar sua lista de prospecção do dia. Evite contatar a base inteira de uma vez.
B7: 2. Aborde pelo WhatsApp de forma direta e educada
B8: Apresente-se, diga que encontrou a loja no polo do Brás e pergunte sobre condições de atacado, pedido mínimo e se enviam para todo o Brasil. Fornecedores respondem melhor a mensagens objetivas do que a textos longos.
B10: 3. Confirme sempre antes de fechar pedido
B11: Esta base é uma lista de contatos para prospecção — não é uma garantia de preço, estoque ou qualidade. Confirme fotos reais do produto, prazo de envio e política de troca antes de pagar. Prefira fornecedores com Instagram ativo e avaliações de outros lojistas.
B13: 4. Priorize por volume de fornecedores
B14: Use a aba 'Painel por Categoria' para identificar onde há mais oferta (ex.: Moda Feminina e Eletrônicos concentram a maior parte da base) e a aba 'Painel por Polo' para escolher qual shopping visitar ou prospectar primeiro.
B16: Avisos importantes
B17: • Os dados foram coletados dos sites oficiais dos polos e são atualizados periodicamente — nomes de loja, telefone e Instagram podem mudar sem aviso.
B18: • Os links de WhatsApp seguem o padrão wa.me e abrem diretamente a conversa; a FORNIX não intermedia negociações, pagamentos ou entregas.
... B22: Dúvidas ou suporte: fale com a equipe FORNIX pelo canal onde você adquiriu esta base.

Sheet Painel por Categoria
B2: Fornecedores por Categoria de Produto
B4: Categoria | C4: Fornecedores | D4: % da Base
B5: Moda Feminina | C5: =COUNTIF('Base Completa'!C2:C1020,B5) -> 482 | D5: =C5/SUM($C$5:$C$26) -> 0.47301276
B6: Eletrônicos e Celulares | C6: =COUNTIF('Base Completa'!C2:C1020,B6) -> 115 | D6: =C6/SUM($C$5:$C$26) -> 0.11285574
B7: Moda Feminina Plus Size | C7: =COUNTIF('Base Completa'!C2:C1020,B7) -> 75 | D7: =C7/SUM($C$5:$C$26) -> 0.07360157
B8: Acessórios e Bijuterias | C8: =COUNTIF('Base Completa'!C2:C1020,B8) -> 65 | D8: =C8/SUM($C$5:$C$26) -> 0.063788027
B9: Moda Jeans | C9: =COUNTIF('Base Completa'!C2:C1020,B9) -> 52 | D9: =C9/SUM($C$5:$C$26) -> 0.051030422
B10: Relógios e Óculos | C10: =COUNTIF('Base Completa'!C2:C1020,B10) -> 31 | D10: =C10/SUM($C$5:$C$26) -> 0.030421982
B11: Perfumaria e Cosméticos | C11: =COUNTIF('Base Completa'!C2:C1020,B11) -> 31 | D11: =C11/SUM($C$5:$C$26) -> 0.030421982
B12: Variedades | C12: =COUNTIF('Base Completa'!C2:C1020,B12) -> 26 | D12: =C12/SUM($C$5:$C$26) -> 0.025515211
B13: Alimentação | C13: =COUNTIF('Base Completa'!C2:C1020,B13) -> 25 | D13: =C13/SUM($C$5:$C$26) -> 0.024533857
B14: Serviços Gerais | C14: =COUNTIF('Base Completa'!C2:C1020,B14) -> 20 | D14: =C14/SUM($C$5:$C$26) -> 0.019627085
B15: Moda Masculina | C15: =COUNTIF('Base Completa'!C2:C1020,B15) -> 19 | D15: =C15/SUM($C$5:$C$26) -> 0.018645731
B16: Outros / Diversos | C16: =COUNTIF('Base Completa'!C2:C1020,B16) -> 18 | D16: =C16/SUM($C$5:$C$26) -> 0.017664377
B17: Moda Infantil / Juvenil | C17: =COUNTIF('Base Completa'!C2:C1020,B17) -> 13 | D17: =C17/SUM($C$5:$C$26) -> 0.012757605
B18: Brinquedos e Games | C18: =COUNTIF('Base Completa'!C2:C1020,B18) -> 13 | D18: =C18/SUM($C$5:$C$26) -> 0.012757605
B19: Moda Fitness | C19: =COUNTIF('Base Completa'!C2:C1020,B19) -> 8 | D19: =C19/SUM($C$5:$C$26) -> 0.0078508342
B20: Moda Praia | C20: =COUNTIF('Base Completa'!C2:C1020,B20) -> 6 | D20: =C20/SUM($C$5:$C$26) -> 0.0058881256
B21: Decoração e Casa | C21: =COUNTIF('Base Completa'!C2:C1020,B21) -> 6 | D21: =C21/SUM($C$5:$C$26) -> 0.0058881256
B22: Moda Íntima | C22: =COUNTIF('Base Completa'!C2:C1020,B22) -> 4 | D22: =C22/SUM($C$5:$C$26) -> 0.0039254171
B23: Moda Festa | C23: =COUNTIF('Base Completa'!C2:C1020,B23) -> 4 | D23: =C23/SUM($C$5:$C$26) -> 0.0039254171
B24: Embalagens, Expositores e Manequins | C24: =COUNTIF('Base Completa'!C2:C1020,B24) -> 3 | D24: =C24/SUM($C$5:$C$26) -> 0.0029440628
B25: Moda Evangélica | C25: =COUNTIF('Base Completa'!C2:C1020,B25) -> 2 | D25: =C25/SUM($C$5:$C$26) -> 0.0019627085
B26: Tecidos e Retalhos | C26: =COUNTIF('Base Completa'!C2:C1020,B26) -> 1 | D26: =C26/SUM($C$5:$C$26) -> 0.00098135427
B27: TOTAL | C27: =SUM(C5:C26) -> 1019

Sheet Painel por Polo
B2: Fornecedores por Polo / Shopping
B4: Polo / Shopping | C4: Fornecedores | D4: % da Base
B5: Galeria Pagé | C5: =COUNTIF('Base Completa'!E2:E1020,B5) -> 287 | D5: =C5/SUM($C$5:$C$10) -> 0.28164868
B6: Shopping Total Brás | C6: =COUNTIF('Base Completa'!E2:E1020,B6) -> 255 | D6: =C6/SUM($C$5:$C$10) -> 0.25024534
B7: Shopping Canindé | C7: =COUNTIF('Base Completa'!E2:E1020,B7) -> 193 | D7: =C7/SUM($C$5:$C$10) -> 0.18940137
B8: Shopping Porto Brás | C8: =COUNTIF('Base Completa'!E2:E1020,B8) -> 157 | D8: =C8/SUM($C$5:$C$10) -> 0.15407262
B9: Shopping All Brás | C9: =COUNTIF('Base Completa'!E2:E1020,B9) -> 105 | D9: =C9/SUM($C$5:$C$10) -> 0.1030422
B10: O Melhor do Brás (Diretório) | C10: =COUNTIF('Base Completa'!E2:E1020,B10) -> 22 | D10: =C10/SUM($C$5:$C$10) -> 0.021589794
B11: TOTAL | C11: =SUM(C5:C10) -> 1019

Sheet Base Completa
A1: Nº | B1: Loja / Fornecedor | C1: Categoria | D1: Segmento Original (fonte) | E1: Polo / Shopping | F1: WhatsApp | G1: Instagram | H1: Site / Link da Loja | I1: Observação (unidade/endereço)
A2: 1 | B2: 2L | C2: Moda Feminina | D2: Moda Feminina | E2: Shopping Total Brás | F2: Abrir WhatsApp | G2: @2l.oficial | H2: Ver loja
A3: 2 | B3: 3 Marias | C3: Moda Feminina | D3: Moda Feminina | E3: Shopping Total Brás | F3: Abrir WhatsApp | G3: @3marias.oficial | H3: Ver loja
A4: 3 | B4: 4Elementos | C4: Moda Feminina | D4: Moda Feminina | E4: Shopping Total Brás | F4: Abrir WhatsApp | G4: @4elementos_28 | H4: Ver loja
A5: 4 | B5: 775 | C5: Acessórios e Bijuterias | D5: Acessórios | E5: Shopping Total Brás | F5: Abrir WhatsApp | G5: @775.oculos | H5: Ver loja
A6: 5 | B6: A BRABA | C6: Moda Feminina | D6: Moda Feminina | E6: Shopping Total Brás | F6: Abrir WhatsApp | G6: @brabaoficialmodas | H6: Ver loja
A7: 6 | B7: A Criativa | C7: Moda Feminina | D7: Moda Feminina | E7: Shopping Total Brás | F7: Abrir WhatsApp | G7: @acriativamodasbras | H7: Ver loja
A8: 7 | B8: A.R JEANS | C8: Moda Infantil / Juvenil | D8: Moda Infantil | E8: Shopping Total Brás | F8: Abrir WhatsApp | G8: @arjeans_oficial | H8: Ver loja
A9: 8 | B9: ABSOLUX JEANS | C9: Moda Jeans | D9: Moda Jeans | E9: Shopping Total Brás | F9: Abrir WhatsApp | G9: @absoluxjeans | H9: Ver loja
A10: 9 | B10: Achados e Perdidos | C10: Moda Feminina | D10: Moda Feminina | E10: Shopping Total Brás | F10: Abrir WhatsApp | G10: @achadoseperdidosestilo | H10: Ver loja
A11: 10 | B11: ADORA | C11: Moda Feminina | D11: Moda Feminina | E11: Shopping Total Brás | F11: Abrir WhatsApp | G11: @adora_oficial | H11: Ver loja
A12: 11 | B12: AESTILOSA | C12: Moda Feminina | D12: Moda Feminina | E12: Shopping Total Brás | F12: Abrir WhatsApp | G12: @aestilosaoficial_bytatimartins | H12: Ver loja
A13: 12 | B13: AFETTO | C13: Moda Feminina | D13: Moda Feminina | E13: Shopping Total Brás | F13: Abrir WhatsApp | G13: @afettomodas | H13: Ver loja
... A40: 39 | B40: D&M STORE | C40: Moda Feminina | D40: Moda Feminina | E40: Shopping Total Brás | F40: Abrir WhatsApp | G40: @lojad.m_store | H40: Ver loja
A41: 40 | B41: D.Na | C41: Moda Feminina | D41: Moda Feminina | E41: Shopping Total Brás | F41: Abrir WhatsApp | H41: Ver loja
A42: 41 | B42: Dafanda | C42: Moda Feminina | D42: Moda Feminina | E42: Shopping Total Brás | F42: Abrir WhatsApp | G42: @dafandabras | H42: Ver loja
A43: 42 | B43: DAJAQUE ATACADO | C43: Moda Feminina | D43: Moda Feminina | E43: Shopping Total Brás | F43: Abrir WhatsApp | G43: @dajaqueatacado | H43: Ver loja
A44: 43 | B44: Dan Dan | C44: Moda Feminina | D44: Moda Feminina | E44: Shopping Total Brás | F44: Abrir WhatsApp | G44: @dandanmoda | H44: Ver loja
A45: 44 | B45: Dandan | C45: Moda Feminina | D45: Moda Feminina | E45: Shopping Total Brás | F45: Abrir WhatsApp | G45: @dandanmoda | H45: Ver loja
A46: 45 | B46: D´Amos | C46: Moda Feminina | D46: Moda Feminina | E46: Shopping Total Brás | F46: Abrir WhatsApp | G46: @modas_de_amos | H46: Ver loja
A47: 46 | B47: D’ Luxo | C47: Moda Feminina | D47: Moda Feminina | E47: Shopping Total Brás | F47: Abrir WhatsApp | G47: @dluxomodas_ | H47: Ver loja
A48: 47 | B48: D’Amos | C48: Moda Feminina | D48: Moda Feminina | E48: Shopping Total Brás | F48: Abrir WhatsApp | G48: @modas_de_amos | H48: Ver loja
A49: 48 | B49: D’bela | C49: Moda Feminina | D49: Moda Feminina | E49: Shopping Total Brás | F49: Abrir WhatsApp | G49: @dbelaa | H49: Ver loja
A50: 49 | B50: D’Ismael | C50: Moda Feminina | D50: Moda Feminina | E50: Shopping Total Brás | F50: Abrir WhatsApp | G50: @d_ismaelmodas | H50: Ver loja
A51: 50 | B51: D’Ismael | C51: Moda Feminina | D51: Moda Feminina | E51: Shopping Total Brás | F51: Abrir WhatsApp | G51: @d_ismaelmodas | H51: Ver loja
A52: 51 | B52: E Fashion | C52: Moda Feminina | D52: Moda Feminina | E52: Shopping Total Brás | F52: Abrir WhatsApp | G52: @e.fashion_oficial | H52: Ver loja
A53: 52 | B53: Eclética Z | C53: Moda Feminina | D53: Moda Feminina | E53: Shopping Total Brás | F53: Abrir WhatsApp | G53: @ecletica_z | H53: Ver loja
... A103: 102 | B103: Irreverente | C103: Moda Feminina | D103: Moda Feminina | E103: Shopping Total Brás | F103: Abrir WhatsApp | G103: @irrev.modas | H103: Ver loja
A104: 103 | B104: Iruma | C104: Moda Feminina | D104: Moda Feminina | E104: Shopping Total Brás | F104: Abrir WhatsApp | H104: Ver loja
A105: 104 | B105: It Curves | C105: Moda Feminina | D105: Moda Feminina | E105: Shopping Total Brás | F105: Abrir WhatsApp | G105: @itcurves | H105: Ver loja
A106: 105 | B106: Jaja Modas | C106: Moda Feminina | D106: Moda Feminina | E106: Shopping Total Brás | F106: Abrir WhatsApp | G106: @jaja_modas | H106: Ver loja
A107: 106 | B107: Jasming Plus | C107: Moda Feminina Plus Size | D107: Moda Plus Size | E107: Shopping Total Brás | F107: Abrir WhatsApp | G107: @jasming.plus | H107: Ver loja
A108: 107 | B108: Jilem Modas | C108: Moda Feminina | D108: Moda Feminina | E108: Shopping Total Brás | F108: Abrir WhatsApp | G108: @jilem_modas | H108: Ver loja
A109: 108 | B109: JIS MODAS | C109: Moda Feminina | D109: Moda Feminina | E109: Shopping Total Brás | F109: Abrir WhatsApp | G109: @jismodas_total | H109: Ver loja
A110: 109 | B110: JK JENNY KIM | C110: Moda Feminina | D110: Moda Feminina | E110: Shopping Total Brás | F110: Abrir WhatsApp | G110: @jennykim.oficial | H110: Ver loja
A111: 110 | B111: JOIAS FORMEHEL | C111: Acessórios e Bijuterias | D111: Acessórios | E111: Shopping Total Brás | F111: Abrir WhatsApp | G111: @joiasformehel | H111: Ver loja
A112: 111 | B112: JOWY | C112: Moda Fitness | D112: Moda Fitness | E112: Shopping Total Brás | F112: Abrir WhatsApp | G112: @jowy.modas | H112: Ver loja
A113: 112 | B113: JOÁ | C113: Moda Feminina | D113: Moda Feminina | E113: Shopping Total Brás | F113: Abrir WhatsApp | G113: @joa.trendsatacado | H113: Ver loja
A114: 113 | B114: JP Perfumes Importados | C114: Perfumaria e Cosméticos | D114: Perfumes | E114: Shopping Total Brás | F114: Abrir WhatsApp | G114: @jpperfumesimportsorig | H114: Ver loja
A115: 114 | B115: JSP MODAS | C115: Moda Feminina | D115: Moda Feminina | E115: Shopping Total Brás | F115: Abrir WhatsApp | G115: @jspmodafeminina | H115: Ver loja
A116: 115 | B116: Ju Modas | C116: Moda Feminina | D116: Moda Feminina | E116: Shopping Total Brás | F116: Abrir WhatsApp | G116: @jumodas_oficial | H116: Ver loja
... A158: 157 | B158: Negra Cor | C158: Moda Feminina | D158: Moda Feminina | E158: Shopping Total Brás | F158: Abrir WhatsApp | G158: @negra.cor | H158: Ver loja
A159: 158 | B159: Negra Cor Comfort | C159: Moda Feminina | D159: Moda Feminina | E159: Shopping Total Brás | G159: @negracor.comfort | H159: Ver loja
A160: 159 | B160: New Anna | C160: Moda Feminina | D160: Moda Feminina | E160: Shopping Total Brás | F160: Abrir WhatsApp | G160: @new_anaoficial | H160: Ver loja
A161: 160 | B161: New Dai | C161: Moda Feminina | D161: Moda Feminina | E161: Shopping Total Brás | F161: Abrir WhatsApp | G161: @new_dai_oficial | H161: Ver loja
A162: 161 | B162: NEW HYPE | C162: Moda Fitness | D162: Moda Fitness | E162: Shopping Total Brás | F162: Abrir WhatsApp | G162: @newhypefit | H162: Ver loja
A163: 162 | B163: Nicat Girls | C163: Moda Feminina | D163: Moda Feminina | E163: Shopping Total Brás | F163: Abrir WhatsApp | G163: @nicatgirls | H163: Ver loja
A164: 163 | B164: OLIVA | C164: Moda Feminina Plus Size | D164: Moda Plus Size | E164: Shopping Total Brás | F164: Abrir WhatsApp | G164: @olivaplussize | H164: Ver loja
A165: 164 | B165: OPPEN STORE | C165: Moda Feminina | D165: Moda Feminina | E165: Shopping Total Brás | F165: Abrir WhatsApp | G165: @oppen.store | H165: Ver loja
A166: 165 | B166: Outono Moda | C166: Moda Feminina | D166: Moda Feminina | E166: Shopping Total Brás | F166: Abrir WhatsApp | G166: @outonomoda_ | H166: Ver loja
A167: 166 | B167: Pacote Rosa | C167: Moda Feminina | D167: Moda Feminina | E167: Shopping Total Brás | F167: Abrir WhatsApp | G167: @pacoterosa | H167: Ver loja
A168: 167 | B168: Padock Brand | C168: Moda Feminina | D168: Moda Feminina | E168: Shopping Total Brás | F168: Abrir WhatsApp | G168: @padock_brand | H168: Ver loja
A169: 168 | B169: Pandol | C169: Moda Feminina | D169: Moda Feminina | E169: Shopping Total Brás | F169: Abrir WhatsApp | G169: @veste_pandol | H169: Ver loja
A170: 169 | B170: Panther Girls | C170: Moda Feminina | D170: Moda Feminina | E170: Shopping Total Brás | F170: Abrir WhatsApp | G170: @loja_panther_girl | H170: Ver loja
A171: 170 | B171: PEROLA | C171: Moda Feminina | D171: Moda Feminina | E171: Shopping Total Brás | F171: Abrir WhatsApp | G171: @perolamodasp | H171: Ver loja
... A239: 238 | B239: Vicks Store | C239: Moda Feminina | D239: Moda Feminina | E239: Shopping Total Brás | F239: Abrir WhatsApp | G239: @vicksstore | H239: Ver loja
A240: 239 | B240: WINNIE | C240: Moda Feminina | D240: Moda Feminina | E240: Shopping Total Brás | G240: @winnie_modas | H240: Ver loja
A241: 240 | B241: WJ Rio | C241: Moda Festa | D241: Moda Festa | E241: Shopping Total Brás | F241: Abrir WhatsApp | G241: @vestido_de_festa_peonia | H241: Ver loja
A242: 241 | B242: WM Cinto em Couro | C242: Acessórios e Bijuterias | D242: Acessórios | E242: Shopping Total Brás | G242: @wmcintoemcouro | H242: Ver loja
A243: 242 | B243: WYLLARA | C243: Moda Feminina | D243: Moda Feminina | E243: Shopping Total Brás | F243: Abrir WhatsApp | G243: @wyllara | H243: Ver loja
A244: 243 | B244: Xamby Confecções | C244: Moda Feminina | D244: Moda Feminina | E244: Shopping Total Brás | F244: Abrir WhatsApp | H244: Ver loja
A245: 244 | B245: YARI OFICIAL | C245: Moda Evangélica | D245: Moda Evangélica | E245: Shopping Total Brás | F245: Abrir WhatsApp | G245: @yarioficiall | H245: Ver loja
A246: 245 | B246: Yegrina | C246: Moda Feminina | D246: Moda Feminina | E246: Shopping Total Brás | F246: Abrir WhatsApp | G246: @yegrinaofc | H246: Ver loja
A247: 246 | B247: Yellon | C247: Moda Feminina | D247: Moda Feminina | E247: Shopping Total Brás | F247: Abrir WhatsApp | G247: @yellonmoda | H247: Ver loja
A248: 247 | B248: Yellow Modas | C248: Moda Festa | D248: Moda Festa | E248: Shopping Total Brás | F248: Abrir WhatsApp | G248: @festasyellow | H248: Ver loja
A249: 248 | B249: You Mariah | C249: Moda Feminina | D249: Moda Feminina | E249: Shopping Total Brás | F249: Abrir WhatsApp | G249: @you.mariah | H249: Ver loja
A250: 249 | B250: Yunico | C250: Moda Feminina | D250: Moda Feminina | E250: Shopping Total Brás | F250: Abrir WhatsApp | G250: @yunico_modas | H250: Ver loja
A251: 250 | B251: ZABAY PERFUMES | C251: Perfumaria e Cosméticos | D251: Perfumes | E251: Shopping Total Brás | F251: Abrir WhatsApp | G251: @zabayimports | H251: Ver loja
A252: 251 | B252: ZHAFRA | C252: Moda Feminina | D252: Moda Feminina | E252: Shopping Total Brás | F252: Abrir WhatsApp | G252: @zhafra_confeccoes | H252: Ver loja
A253: 252 | B253: ZNL | C253: Moda Feminina | D253: Moda Feminina | E253: Shopping Total Brás | F253: Abrir WhatsApp | G253: @moda_znl | H253: Ver loja
A254: 253 | B254: Zoe Store | C254: Moda Feminina | D254: Moda Feminina | E254: Shopping Total Brás | F254: Abrir WhatsApp | G254: @zoestore___ | H254: Ver loja
A255: 254 | B255: ÁGAPE | C255: Moda Feminina | D255: Moda Feminina | E255: Shopping Total Brás | F255: Abrir WhatsApp | G255: @agapeestillodamo | H255: Ver loja
A256: 255 | B256: Éclairé Store | C256: Moda Feminina | D256: Moda Feminina | E256: Shopping Total Brás | F256: Abrir WhatsApp | G256: @eclaire_store | H256: Ver loja
... A261: 260 | B261: ALAN BRINQUEDOS E ELETRÔNICOS | C261: Brinquedos e Games | D261: Brinquedos | E261: Galeria Pagé | F261: Abrir WhatsApp | G261: @alanbrinquedose | H261: Ver loja
A262: 261 | B262: ALEX RELÓGIOS | C262: Relógios e Óculos | D262: Relógio | E262: Galeria Pagé | F262: Abrir WhatsApp | H262: Ver loja
A263: 262 | B263: ALMEIDA CRUZ | C263: Acessórios e Bijuterias | D263: Acessórios Para Celular | E263: Galeria Pagé | F263: Abrir WhatsApp | G263: @almeidacruzbr | H263: Ver loja
A264: 263 | B264: ALPHA CASE | C264: Acessórios e Bijuterias | D264: Acessórios Para Celular | E264: Galeria Pagé | F264: Abrir WhatsApp | G264: @alphacase_65 | H264: Ver loja
A265: 264 | B265: ALÍCIA BIJOUTERIAS | C265: Acessórios e Bijuterias | D265: Bijuterias / Jóias E Acessórios | E265: Galeria Pagé | F265: Abrir WhatsApp | G265: @aliciafolheadoss | H265: Ver loja
A266: 265 | B266: AMAZONA | C266: Perfumaria e Cosméticos | D266: Cosméticos / Maquiagem E Perfumaria | E266: Galeria Pagé | F266: Abrir WhatsApp | G266: @amazonacosmeticosbarbaria | H266: Ver loja
A267: 266 | B267: AMAZONA BARBER SHOP | C267: Serviços Gerais | D267: Barbearia / Cabelos / E Unhas | E267: Galeria Pagé | F267: Abrir WhatsApp | G267: @amazonacosmeticosbarbearia | H267: Ver loja
A268: 267 | B268: AMAZONA HAIR | C268: Serviços Gerais | D268: Barbearia / Cabelos / E Unhas | E268: Galeria Pagé | F268: Abrir WhatsApp | G268: @amazonacosmeticosbarbearia | H268: Ver loja
A269: 268 | B269: ANA ATACADO E VAREJO | C269: Eletrônicos e Celulares | D269: Eletrônicos | E269: Galeria Pagé | F269: Abrir WhatsApp | G269: @ANJO666888 | H269: Ver loja
A270: 269 | B270: ANNA GRAVAÇÕES | C270: Variedades | D270: Variedades | E270: Galeria Pagé | F270: Abrir WhatsApp | G270: @. | H270: Ver loja
A271: 270 | B271: AQ SHOPPING | C271: Eletrônicos e Celulares | D271: Eletrônicos | E271: Galeria Pagé | F271: Abrir WhatsApp | G271: @aq_shopping_1001 | H271: Ver loja
A272: 271 | B272: AROMAPONTOCOM | C272: Perfumaria e Cosméticos | D272: Perfumaria | E272: Galeria Pagé | F272: Abrir WhatsApp | G272: @aromaperfumespontocom | H272: Ver loja
A273: 272 | B273: AROMÁTICO | C273: Perfumaria e Cosméticos | D273: Perfumaria | E273: Galeria Pagé | F273: Abrir WhatsApp | G273: @aromatico.br | H273: Ver loja
A274: 273 | B274: ARVORE DO CAFÉ | C274: Alimentação | D274: Alimentação | E274: Galeria Pagé | F274: Abrir WhatsApp | G274: @arvoredocafe2023 | H274: Ver loja
... A279: 278 | B279: AÇAÍ DA JU | C279: Alimentação | D279: Alimentação | E279: Galeria Pagé | F279: Abrir WhatsApp | G279: @acaidaju3216 | H279: Ver loja
A280: 279 | B280: B&W | C280: Eletrônicos e Celulares | D280: Eletrônicos | E280: Galeria Pagé | F280: Abrir WhatsApp | H280: Ver loja
A281: 280 | B281: BAIHUO CITY ELETRONICOS | C281: Eletrônicos e Celulares | D281: Eletrônicos | E281: Galeria Pagé | F281: Abrir WhatsApp | G281: @baihuocityeletronicosoficial | H281: Ver loja
A282: 281 | B282: BAM BAM CHICKEN | C282: Alimentação | D282: Alimentação | E282: Galeria Pagé | F282: Abrir WhatsApp | G282: @bambam_chickenbras | H282: Ver loja
A283: 282 | B283: BAZAR JOINHA | C283: Eletrônicos e Celulares | D283: Eletrônicos | E283: Galeria Pagé | F283: Abrir WhatsApp | G283: @bazar.joinha | H283: Ver loja
A284: 283 | B284: BEIRUT CAPAS | C284: Acessórios e Bijuterias | D284: Acessórios Para Celular | E284: Galeria Pagé | F284: Abrir WhatsApp | G284: @beirutcapas | H284: Ver loja
A285: 284 | B285: BELLE VIE | C285: Relógios e Óculos | D285: Ótica | E285: Galeria Pagé | F285: Abrir WhatsApp | G285: @belleviebras | H285: Ver loja
A286: 285 | B286: BENEDO | C286: Eletrônicos e Celulares | D286: Eletrônicos | E286: Galeria Pagé | F286: Abrir WhatsApp | G286: @benedo_relogios | H286: Ver loja
A287: 286 | B287: BEST SHOP | C287: Eletrônicos e Celulares | D287: Celular | E287: Galeria Pagé | F287: Abrir WhatsApp | G287: @spbestshop | H287: Ver loja
A288: 287 | B288: BG BRINQUEDOS | C288: Brinquedos e Games | D288: Brinquedos | E288: Galeria Pagé | F288: Abrir WhatsApp | G288: @bg.brinquedos | H288: Ver loja
A289: 288 | B289: BIANCA | C289: Relógios e Óculos | D289: Relógio | E289: Galeria Pagé | F289: Abrir WhatsApp | H289: Ver loja
A290: 289 | B290: BLACK STORY | C290: Eletrônicos e Celulares | D290: Celular | E290: Galeria Pagé | F290: Abrir WhatsApp | G290: @blackstory_oficial | H290: Ver loja
A291: 290 | B291: BOM & BARATO | C291: Eletrônicos e Celulares | D291: Eletrônicos | E291: Galeria Pagé | F291: Abrir WhatsApp | G291: @. | H291: Ver loja
...

Sheet Total Brás
A1: Shopping Total Brás — 255 fornecedores mapeados
A2: Nº | B2: Loja / Fornecedor | C2: Categoria | D2: WhatsApp | E2: Instagram | F2: Site / Link | G2: Observação
A3: 1 | B3: 2L | C3: Moda Feminina | D3: Abrir WhatsApp | E3: @2l.oficial | F3: Ver loja
A4: 2 | B4: 3 Marias | C4: Moda Feminina | D4: Abrir WhatsApp | E4: @3marias.oficial | F4: Ver loja
A5: 3 | B5: 4Elementos | C5: Moda Feminina | D5: Abrir WhatsApp | E5: @4elementos_28 | F5: Ver loja
A6: 4 | B6: 775 | C6: Acessórios e Bijuterias | D6: Abrir WhatsApp | E6: @775.oculos | F6: Ver loja
A7: 5 | B7: A BRABA | C7: Moda Feminina | D7: Abrir WhatsApp | E7: @brabaoficialmodas | F7: Ver loja
A8: 6 | B8: A Criativa | C8: Moda Feminina | D8: Abrir WhatsApp | E8: @acriativamodasbras | F8: Ver loja
A9: 7 | B9: A.R JEANS | C9: Moda Infantil / Juvenil | D9: Abrir WhatsApp | E9: @arjeans_oficial | F9: Ver loja
A10: 8 | B10: ABSOLUX JEANS | C10: Moda Jeans | D10: Abrir WhatsApp | E10: @absoluxjeans | F10: Ver loja
A11: 9 | B11: Achados e Perdidos | C11: Moda Feminina | D11: Abrir WhatsApp | E11: @achadoseperdidosestilo | F11: Ver loja
A12: 10 | B12: ADORA | C12: Moda Feminina | D12: Abrir WhatsApp | E12: @adora_oficial | F12: Ver loja
A13: 11 | B13: AESTILOSA | C13: Moda Feminina | D13: Abrir WhatsApp | E13: @aestilosaoficial_bytatimartins | F13: Ver loja
A14: 12 | B14: AFETTO | C14: Moda Feminina | D14: Abrir WhatsApp | E14: @afettomodas | F14: Ver loja
... A41: 39 | B41: D&M STORE | C41: Moda Feminina | D41: Abrir WhatsApp | E41: @lojad.m_store | F41: Ver loja
A42: 40 | B42: D.Na | C42: Moda Feminina | D42: Abrir WhatsApp | F42: Ver loja
A43: 41 | B43: Dafanda | C43: Moda Feminina | D43: Abrir WhatsApp | E43: @dafandabras | F43: Ver loja
A44: 42 | B44: DAJAQUE ATACADO | C44: Moda Feminina | D44: Abrir WhatsApp | E44: @dajaqueatacado | F44: Ver loja
A45: 43 | B45: Dan Dan | C45: Moda Feminina | D45: Abrir WhatsApp | E45: @dandanmoda | F45: Ver loja
A46: 44 | B46: Dandan | C46: Moda Feminina | D46: Abrir WhatsApp | E46: @dandanmoda | F46: Ver loja
A47: 45 | B47: D´Amos | C47: Moda Feminina | D47: Abrir WhatsApp | E47: @modas_de_amos | F47: Ver loja
A48: 46 | B48: D’ Luxo | C48: Moda Feminina | D48: Abrir WhatsApp | E48: @dluxomodas_ | F48: Ver loja
A49: 47 | B49: D’Amos | C49: Moda Feminina | D49: Abrir WhatsApp | E49: @modas_de_amos | F49: Ver loja
A50: 48 | B50: D’bela | C50: Moda Feminina | D50: Abrir WhatsApp | E50: @dbelaa | F50: Ver loja
A51: 49 | B51: D’Ismael | C51: Moda Feminina | D51: Abrir WhatsApp | E51: @d_ismaelmodas | F51: Ver loja
A52: 50 | B52: D’Ismael | C52: Moda Feminina | D52: Abrir WhatsApp | E52: @d_ismaelmodas | F52: Ver loja
A53: 51 | B53: E Fashion | C53: Moda Feminina | D53: Abrir WhatsApp | E53: @e.fashion_oficial | F53: Ver loja
A54: 52 | B54: Eclética Z | C54: Moda Feminina | D54: Abrir WhatsApp | E54: @ecletica_z | F54: Ver loja
... A104: 102 | B104: Irreverente | C104: Moda Feminina | D104: Abrir WhatsApp | E104: @irrev.modas | F104: Ver loja
A105: 103 | B105: Iruma | C105: Moda Feminina | D105: Abrir WhatsApp | F105: Ver loja
A106: 104 | B106: It Curves | C106: Moda Feminina | D106: Abrir WhatsApp | E106: @itcurves | F106: Ver loja
A107: 105 | B107: Jaja Modas | C107: Moda Feminina | D107: Abrir WhatsApp | E107: @jaja_modas | F107: Ver loja
A108: 106 | B108: Jasming Plus | C108: Moda Feminina Plus Size | D108: Abrir WhatsApp | E108: @jasming.plus | F108: Ver loja
A109: 107 | B109: Jilem Modas | C109: Moda Feminina | D109: Abrir WhatsApp | E109: @jilem_modas | F109: Ver loja
A110: 108 | B110: JIS MODAS | C110: Moda Feminina | D110: Abrir WhatsApp | E110: @jismodas_total | F110: Ver loja
A111: 109 | B111: JK JENNY KIM | C111: Moda Feminina | D111: Abrir WhatsApp | E111: @jennykim.oficial | F111: Ver loja
A112: 110 | B112: JOIAS FORMEHEL | C112: Acessórios e Bijuterias | D112: Abrir WhatsApp | E112: @joiasformehel | F112: Ver loja
A113: 111 | B113: JOWY | C113: Moda Fitness | D113: Abrir WhatsApp | E113: @jowy.modas | F113: Ver loja
A114: 112 | B114: JOÁ | C114: Moda Feminina | D114: Abrir WhatsApp | E114: @joa.trendsatacado | F114: Ver loja
A115: 113 | B115: JP Perfumes Importados | C115: Perfumaria e Cosméticos | D115: Abrir WhatsApp | E115: @jpperfumesimportsorig | F115: Ver loja
A116: 114 | B116: JSP MODAS | C116: Moda Feminina | D116: Abrir WhatsApp | E116: @jspmodafeminina | F116: Ver loja
A117: 115 | B117: Ju Modas | C117: Moda Feminina | D117: Abrir WhatsApp | E117: @jumodas_oficial | F117: Ver loja
... A159: 157 | B159: Negra Cor | C159: Moda Feminina | D159: Abrir WhatsApp | E159: @negra.cor | F159: Ver loja
A160: 158 | B160: Negra Cor Comfort | C160: Moda Feminina | E160: @negracor.comfort | F160: Ver loja
A161: 159 | B161: New Anna | C161: Moda Feminina | D161: Abrir WhatsApp | E161: @new_anaoficial | F161: Ver loja
A162: 160 | B162: New Dai | C162: Moda Feminina | D162: Abrir WhatsApp | E162: @new_dai_oficial | F162: Ver loja
A163: 161 | B163: NEW HYPE | C163: Moda Fitness | D163: Abrir WhatsApp | E163: @newhypefit | F163: Ver loja
A164: 162 | B164: Nicat Girls | C164: Moda Feminina | D164: Abrir WhatsApp | E164: @nicatgirls | F164: Ver loja
A165: 163 | B165: OLIVA | C165: Moda Feminina Plus Size | D165: Abrir WhatsApp | E165: @olivaplussize | F165: Ver loja
A166: 164 | B166: OPPEN STORE | C166: Moda Feminina | D166: Abrir WhatsApp | E166: @oppen.store | F166: Ver loja
A167: 165 | B167: Outono Moda | C167: Moda Feminina | D167: Abrir WhatsApp | E167: @outonomoda_ | F167: Ver loja
A168: 166 | B168: Pacote Rosa | C168: Moda Feminina | D168: Abrir WhatsApp | E168: @pacoterosa | F168: Ver loja
A169: 167 | B169: Padock Brand | C169: Moda Feminina | D169: Abrir WhatsApp | E169: @padock_brand | F169: Ver loja
A170: 168 | B170: Pandol | C170: Moda Feminina | D170: Abrir WhatsApp | E170: @veste_pandol | F170: Ver loja
A171: 169 | B171: Panther Girls | C171: Moda Feminina | D171: Abrir WhatsApp | E171: @loja_panther_girl | F171: Ver loja
A172: 170 | B172: PEROLA | C172: Moda Feminina | D172: Abrir WhatsApp | E172: @perolamodasp | F172: Ver loja
... A240: 238 | B240: Vicks Store | C240: Moda Feminina | D240: Abrir WhatsApp | E240: @vicksstore | F240: Ver loja
A241: 239 | B241: WINNIE | C241: Moda Feminina | E241: @winnie_modas | F241: Ver loja
A242: 240 | B242: WJ Rio | C242: Moda Festa | D242: Abrir WhatsApp | E242: @vestido_de_festa_peonia | F242: Ver loja
A243: 241 | B243: WM Cinto em Couro | C243: Acessórios e Bijuterias | E243: @wmcintoemcouro | F243: Ver loja
A244: 242 | B244: WYLLARA | C244: Moda Feminina | D244: Abrir WhatsApp | E244: @wyllara | F244: Ver loja
A245: 243 | B245: Xamby Confecções | C245: Moda Feminina | D245: Abrir WhatsApp | F245: Ver loja
A246: 244 | B246: YARI OFICIAL | C246: Moda Evangélica | D246: Abrir WhatsApp | E246: @yarioficiall | F246: Ver loja
A247: 245 | B247: Yegrina | C247: Moda Feminina | D247: Abrir WhatsApp | E247: @yegrinaofc | F247: Ver loja
A248: 246 | B248: Yellon | C248: Moda Feminina | D248: Abrir WhatsApp | E248: @yellonmoda | F248: Ver loja
A249: 247 | B249: Yellow Modas | C249: Moda Festa | D249: Abrir WhatsApp | E249: @festasyellow | F249: Ver loja
A250: 248 | B250: You Mariah | C250: Moda Feminina | D250: Abrir WhatsApp | E250: @you.mariah | F250: Ver loja
A251: 249 | B251: Yunico | C251: Moda Feminina | D251: Abrir WhatsApp | E251: @yunico_modas | F251: Ver loja
A252: 250 | B252: ZABAY PERFUMES | C252: Perfumaria e Cosméticos | D252: Abrir WhatsApp | E252: @zabayimports | F252: Ver loja
A253: 251 | B253: ZHAFRA | C253: Moda Feminina | D253: Abrir WhatsApp | E253: @zhafra_confeccoes | F253: Ver loja
A254: 252 | B254: ZNL | C254: Moda Feminina | D254: Abrir WhatsApp | E254: @moda_znl | F254: Ver loja
A255: 253 | B255: Zoe Store | C255: Moda Feminina | D255: Abrir WhatsApp | E255: @zoestore___ | F255: Ver loja
A256: 254 | B256: ÁGAPE | C256: Moda Feminina | D256: Abrir WhatsApp | E256: @agapeestillodamo | F256: Ver loja
A257: 255 | B257: Éclairé Store | C257: Moda Feminina | D257: Abrir WhatsApp | E257: @eclaire_store | F257: Ver loja

Sheet Pagé
A1: Galeria Pagé — 287 fornecedores mapeados
A2: Nº | B2: Loja / Fornecedor | C2: Categoria | D2: WhatsApp | E2: Instagram | F2: Site / Link | G2: Observação
A3: 1 | B3: #CHAMA | C3: Eletrônicos e Celulares | D3: Abrir WhatsApp | E3: @hashtagchama | F3: Ver loja
A4: 2 | B4: 3E EAST EMPORIUM ELETRÔNICOS | C4: Eletrônicos e Celulares | D4: Abrir WhatsApp | E4: @3eeastemporium | F4: Ver loja
A5: 3 | B5: 99º C ELETRÔNICOS E ACESSÓRIOS | C5: Eletrônicos e Celulares | D5: Abrir WhatsApp | E5: @99_graus_distribuidora | F5: Ver loja
A6: 4 | B6: AL TANUR | C6: Alimentação | D6: Abrir WhatsApp | E6: @altanur_pagee | F6: Ver loja
A7: 5 | B7: ALAN BRINQUEDOS E ELETRÔNICOS | C7: Brinquedos e Games | D7: Abrir WhatsApp | E7: @alanbrinquedose | F7: Ver loja
A8: 6 | B8: ALEX RELÓGIOS | C8: Relógios e Óculos | D8: Abrir WhatsApp | F8: Ver loja
A9: 7 | B9: ALMEIDA CRUZ | C9: Acessórios e Bijuterias | D9: Abrir WhatsApp | E9: @almeidacruzbr | F9: Ver loja
A10: 8 | B10: ALPHA CASE | C10: Acessórios e Bijuterias | D10: Abrir WhatsApp | E10: @alphacase_65 | F10: Ver loja
A11: 9 | B11: ALÍCIA BIJOUTERIAS | C11: Acessórios e Bijuterias | D11: Abrir WhatsApp | E11: @aliciafolheadoss | F11: Ver loja
A12: 10 | B12: AMAZONA | C12: Perfumaria e Cosméticos | D12: Abrir WhatsApp | E12: @amazonacosmeticosbarbaria | F12: Ver loja
A13: 11 | B13: AMAZONA BARBER SHOP | C13: Serviços Gerais | D13: Abrir WhatsApp | E13: @amazonacosmeticosbarbearia | F13: Ver loja
A14: 12 | B14: AMAZONA HAIR | C14: Serviços Gerais | D14: Abrir WhatsApp | E14: @amazonacosmeticosbarbearia | F14: Ver loja
A15: 13 | B15: ANA ATACADO E VAREJO | C15: Eletrônicos e Celulares | D15: Abrir WhatsApp | E15: @ANJO666888 | F15: Ver loja
A16: 14 | B16: ANNA GRAVAÇÕES | C16: Variedades | D16: Abrir WhatsApp | E16: @. | F16: Ver loja
A17: 15 | B17: AQ SHOPPING | C17: Eletrônicos e Celulares | D17: Abrir WhatsApp | E17: @aq_shopping_1001 | F17: Ver loja
A18: 16 | B18: AROMAPONTOCOM | C18: Perfumaria e Cosméticos | D18: Abrir WhatsApp | E18: @aromaperfumespontocom | F18: Ver loja
A19: 17 | B19: AROMÁTICO | C19: Perfumaria e Cosméticos | D19: Abrir WhatsApp | E19: @aromatico.br | F19: Ver loja
A20: 18 | B20: ARVORE DO CAFÉ | C20: Alimentação | D20: Abrir WhatsApp | E20: @arvoredocafe2023 | F20: Ver loja
... A25: 23 | B25: AÇAÍ DA JU | C25: Alimentação | D25: Abrir WhatsApp | E25: @acaidaju3216 | F25: Ver loja
A26: 24 | B26: B&W | C26: Eletrônicos e Celulares | D26: Abrir WhatsApp | F26: Ver loja
A27: 25 | B27: BAIHUO CITY ELETRONICOS | C27: Eletrônicos e Celulares | D27: Abrir WhatsApp | E27: @baihuocityeletronicosoficial | F27: Ver loja
A28: 26 | B28: BAM BAM CHICKEN | C28: Alimentação | D28: Abrir WhatsApp | E28: @bambam_chickenbras | F28: Ver loja
A29: 27 | B29: BAZAR JOINHA | C29: Eletrônicos e Celulares | D29: Abrir WhatsApp | E29: @bazar.joinha | F29: Ver loja
A30: 28 | B30: BEIRUT CAPAS | C30: Acessórios e Bijuterias | D30: Abrir WhatsApp | E30: @beirutcapas | F30: Ver loja
A31: 29 | B31: BELLE VIE | C31: Relógios e Óculos | D31: Abrir WhatsApp | E31: @belleviebras | F31: Ver loja
A32: 30 | B32: BENEDO | C32: Eletrônicos e Celulares | D32: Abrir WhatsApp | E32: @benedo_relogios | F32: Ver loja
A33: 31 | B33: BEST SHOP | C33: Eletrônicos e Celulares | D33: Abrir WhatsApp | E33: @spbestshop | F33: Ver loja
A34: 32 | B34: BG BRINQUEDOS | C34: Brinquedos e Games | D34: Abrir WhatsApp | E34: @bg.brinquedos | F34: Ver loja
A35: 33 | B35: BIANCA | C35: Relógios e Óculos | D35: Abrir WhatsApp | F35: Ver loja
A36: 34 | B36: BLACK STORY | C36: Eletrônicos e Celulares | D36: Abrir WhatsApp | E36: @blackstory_oficial | F36: Ver loja
A37: 35 | B37: BOM & BARATO | C37: Eletrônicos e Celulares | D37: Abrir WhatsApp | E37: @. | F37: Ver loja
A38: 36 | B38: BOX 1124/1125 | C38: Eletrônicos e Celulares | D38: Abrir WhatsApp | E38: @panda835799 | F38: Ver loja
A39: 37 | B39: BTV LIVE | C39: Eletrônicos e Celulares | D39: Abrir WhatsApp | E39: @oficial.btvlive | F39: Ver loja
A40: 38 | B40: BURGUER KING | C40: Alimentação | D40: Abrir WhatsApp | F40: Ver loja
A41: 39 | B41: BURGUER KING - Q | C41: Alimentação | D41: Abrir WhatsApp | E41: @. | F41: Ver loja
A42: 40 | B42: C&Y | C42: Perfumaria e Cosméticos | D42: Abrir WhatsApp | E42: @artedeunha_olinrovi | F42: Ver loja
A43: 41 | B43: C.C ATACADO E VAREJO | C43: Acessórios e Bijuterias | D43: Abrir WhatsApp | F43: Ver loja
A44: 42 | B44: CAMILA RELÓGIOS | C44: Relógios e Óculos | D44: Abrir WhatsApp | E44: @camila.relogios | F44: Ver loja
A45: 43 | B45: CAPINHAS E PELÍCULAS | C45: Acessórios e Bijuterias | D45: Abrir WhatsApp | E45: @galeriapagebrast046 | F45: Ver loja
A46: 44 | B46: CAPITAL DOS BRINQUEDOS | C46: Brinquedos e Games | D46: Abrir WhatsApp | E46: @_capitaldosbrinquedos | F46: Ver loja
A47: 45 | B47: CAROL MODAS JEANS | C47: Outros / Diversos | D47: Abrir WhatsApp | E47: @carolmodas_jeans | F47: Ver loja
A48: 46 | B48: CASA DAS EMBALAGENS | C48: Outros / Diversos | D48: Abrir WhatsApp | E48: @casadasembalagensbras | F48: Ver loja
A49: 47 | B49: CASA DOS ACESSÓRIOS | C49: Eletrônicos e Celulares | D49: Abrir WhatsApp | F49: Ver loja
A50: 48 | B50: CENTRAL DOS BRINQUEDOS | C50: Brinquedos e Games | D50: Abrir WhatsApp | E50: @central_dos_brinquedos | F50: Ver loja
A51: 49 | B51: CHEF TABACARIA | C51: Serviços Gerais | D51: Abrir WhatsApp | E51: @chef.etabacaria | F51: Ver loja
A52: 50 | B52: CHIC725 ÓCULOS E PERFUMES | C52: Perfumaria e Cosméticos | D52: Abrir WhatsApp | E52: @lisa.chic.top | F52: Ver loja
A53: 51 | B53: CHINA CFTV | C53: Eletrônicos e Celulares | D53: Abrir WhatsApp | E53: @alexchinacftv | F53: Ver loja
A54: 52 | B54: CHLOE CAPA | C54: Acessórios e Bijuterias | D54: Abrir WhatsApp | E54: @CHOLE_CAPAS61 | F54: Ver loja
A55: 53 | B55: CiCiMODA | C55: Relógios e Óculos | D55: Abrir WhatsApp | E55: @oticacicimoda | F55: Ver loja
A56: 54 | B56: COCO MIX | C56: Eletrônicos e Celulares | D56: Abrir WhatsApp | E56: @cocomix.shop | F56: Ver loja
A57: 55 | B57: CRISTINA | C57: Eletrônicos e Celulares | D57: Abrir WhatsApp | F57: Ver loja
A58: 56 | B58: CTR+ CONTROLES REMOTO E ACESSÓRIOS ELETRÔNICOS | C58: Eletrônicos e Celulares | D58: Abrir WhatsApp | E58: @controlmais.controlesevariados | F58: Ver loja
A59: 57 | B59: DA HORA CELL | C59: Eletrônicos e Celulares | D59: Abrir WhatsApp | E59: @da_hora_cel | F59: Ver loja
A60: 58 | B60: DA HORA CELL ACESSORIOS TERMICO | C60: Relógios e Óculos | D60: Abrir WhatsApp | E60: @. | F60: Ver loja
A61: 59 | B61: DAMA HAIR | C61: Variedades | D61: Abrir WhatsApp | E61: @dama_hair_cosmetic_oficial | F61: Ver loja
A62: 60 | B62: DARLING | C62: Variedades | D62: Abrir WhatsApp | E62: @. | F62: Ver loja
A63: 61 | B63: DELTA CELL | C63: Eletrônicos e Celulares | D63: Abrir WhatsApp | E63: @delta_cellacessorios | F63: Ver loja
A64: 62 | B64: DEVIA | C64: Acessórios e Bijuterias | D64: Abrir WhatsApp | F64: Ver loja
A65: 63 | B65: DIFERENÇA | C65: Outros / Diversos | D65: Abrir WhatsApp | E65: @diferencadenim | F65: Ver loja
A66: 64 | B66: DP LED LIGHT | C66: Decoração e Casa | D66: Abrir WhatsApp | E66: @h.t.importech | F66: Ver loja
A67: 65 | B67: E&E EMMY RELÓGIOS E ÓCULOS | C67: Relógios e Óculos | D67: Abrir WhatsApp | F67: Ver loja
A68: 66 | B68: EDA | C68: Eletrônicos e Celulares | D68: Abrir WhatsApp | E68: @sunny_liang06 | F68: Ver loja
A69: 67 | B69: EDEN | C69: Eletrônicos e Celulares | D69: Abrir WhatsApp | E69: @edenmecardo_oficial | F69: Ver loja
A70: 68 | B70: ELY FASHION KIDS | C70: Outros / Diversos | D70: Abrir WhatsApp | E70: @ely.fashionkids | F70: Ver loja
A71: 69 | B71: ERIK ACESSORIOS | C71: Relógios e Óculos | D71: Abrir WhatsApp | E71: @ERIK_ACESSORIOST185 | F71: Ver loja
A72: 70 | B72: ESPAÇO LASER | C72: Serviços Gerais | D72: Abrir WhatsApp | E72: @espacogaleriapage | F72: Ver loja
A73: 71 | B73: ESTER 007 | C73: Eletrônicos e Celulares | D73: Abrir WhatsApp | E73: @ester.007_luo | F73: Ver loja
A74: 72 | B74: FAM IMPORTAÇÃO | C74: Acessórios e Bijuterias | D74: Abrir WhatsApp | E74: @ FAM_IMPORTACAO_BRAS | F74: Ver loja
A75: 73 | B75: FAN ELETRÔNICOS | C75: Eletrônicos e Celulares | D75: Abrir WhatsApp | E75: @ fan__eletronicos | F75: Ver loja
A76: 74 | B76: FELAGGIL DISTRIBUIDORA | C76: Perfumaria e Cosméticos | D76: Abrir WhatsApp | E76: @leilacalefe_felaggil | F76: Ver loja
A77: 75 | B77: FELIPE ATAC. E VAREJO | C77: Eletrônicos e Celulares | D77: Abrir WhatsApp | F77: Ver loja
A78: 76 | B78: FITNESS OPEN | C78: Outros / Diversos | D78: Abrir WhatsApp | E78: @fitnessopenoficial_ | F78: Ver loja
A79: 77 | B79: Fix na Hora | C79: Eletrônicos e Celulares | D79: Abrir WhatsApp | E79: @fixnahora | F79: Ver loja
A80: 78 | B80: FLASH TIGER | C80: Eletrônicos e Celulares | D80: Abrir WhatsApp | E80: @flashtiger | F80: Ver loja
A81: 79 | B81: FNX TABACARIA | C81: Serviços Gerais | D81: Abrir WhatsApp | E81: @ fnxoficialsp | F81: Ver loja
A82: 80 | B82: FOLHA OURO | C82: Eletrônicos e Celulares | D82: Abrir WhatsApp | E82: @folha_ouro | F82: Ver loja
A83: 81 | B83: FREE STYLE | C83: Acessórios e Bijuterias | D83: Abrir WhatsApp | E83: @capasfreestyle | F83: Ver loja
A84: 82 | B84: G SHIELD | C84: Eletrônicos e Celulares | D84: Abrir WhatsApp | E84: @ATACADOGSHIELDBR | F84: Ver loja
A85: 83 | B85: GAJEX | C85: Acessórios e Bijuterias | D85: Abrir WhatsApp | E85: @gajex_distribuidora | F85: Ver loja
A86: 84 | B86: GLÉCIA ARRUDA | C86: Eletrônicos e Celulares | D86: Abrir WhatsApp | E86: @. | F86: Ver loja
A87: 85 | B87: GOBAGS | C87: Acessórios e Bijuterias | D87: Abrir WhatsApp | E87: @gobagsacessorios | F87: Ver loja
A88: 86 | B88: GOLDEN | C88: Eletrônicos e Celulares | D88: Abrir WhatsApp | E88: @goldenassistencia | F88: Ver loja
A89: 87 | B89: GRASSE | C89: Perfumaria e Cosméticos | D89: Abrir WhatsApp | E89: @parfumgrasse | F89: Ver loja
... A92: 90 | B92: H | C92: Relógios e Óculos | D92: Abrir WhatsApp | E92: @zhuni_hao_yun | F92: Ver loja
A93: 91 | B93: H MASTOM | C93: Eletrônicos e Celulares | D93: Abrir WhatsApp | F93: Ver loja
A94: 92 | B94: H-IVY | C94: Relógios e Óculos | D94: Abrir WhatsApp | E94: @. | F94: Ver loja
A95: 93 | B95: HELEN PRESENTES | C95: Eletrônicos e Celulares | D95: Abrir WhatsApp | E95: @helen_presentes | F95: Ver loja
A96: 94 | B96: HEYLI ELETRONICOS | C96: Eletrônicos e Celulares | D96: Abrir WhatsApp | E96: @heyli.oficial | F96: Ver loja
A97: 95 | B97: HONG DA RELÓGIO | C97: Relógios e Óculos | D97: Abrir WhatsApp | E97: @tu_fang_joalheria | F97: Ver loja
A98: 96 | B98: HUANG | C98: Acessórios e Bijuterias | D98: Abrir WhatsApp | E98: @HUANG_CAPAS | F98: Ver loja
A99: 97 | B99: INHOU | C99: Eletrônicos e Celulares | D99: Abrir WhatsApp | E99: @. | F99: Ver loja
A100: 98 | B100: INOVA | C100: Variedades | D100: Abrir WhatsApp | E100: @INOVA1049PAGEBRAS | F100: Ver loja
A101: 99 | B101: INOVA | C101: Eletrônicos e Celulares | D101: Abrir WhatsApp | E101: @. | F101: Ver loja
A102: 100 | B102: INOVA TALINE | C102: Eletrônicos e Celulares | D102: Abrir WhatsApp | E102: @. | F102: Ver loja
A103: 101 | B103: ISABELLE DUPONT | C103: Perfumaria e Cosméticos | D103: Abrir WhatsApp | E103: @Isabellelabelleofc | F103: Ver loja
A104: 102 | B104: JACKSON RELOJOARIA | C104: Relógios e Óculos | D104: Abrir WhatsApp | F104: Ver loja
A105: 103 | B105: JANE PERFUMARIA | C105: Perfumaria e Cosméticos | D105: Abrir WhatsApp | E105: @cheirocomch | F105: Ver loja
A106: 104 | B106: JIN | C106: Acessórios e Bijuterias | D106: Abrir WhatsApp | E106: @luckystar966653361 | F106: Ver loja
...

Sheet Canindé
A1: Shopping Canindé — 193 fornecedores mapeados
A2: Nº | B2: Loja / Fornecedor | C2: Categoria | D2: WhatsApp | E2: Instagram | F2: Site / Link | G2: Observação
A3: 1 | B3: AF MODA FESTA | C3: Moda Feminina | D3: Abrir WhatsApp | E3: @af_modafesta | F3: Ver loja
A4: 2 | B4: AGUERO MODAS / AGUERO PREMIUM | C4: Moda Feminina | D4: Abrir WhatsApp | E4: @wr.%20aguero%20wr.aguero%20premium | F4: Ver loja
A5: 3 | B5: AGUERO MODAS / AGUERO PREMIUM | C5: Moda Feminina | D5: Abrir WhatsApp | E5: @wr.%20aguero%20wr.aguero%20premium | F5: Ver loja
A6: 4 | B6: AL MODASS | C6: Moda Feminina | D6: Abrir WhatsApp | E6: @almodass_ | F6: Ver loja
A7: 5 | B7: ALASKA | C7: Moda Feminina | D7: Abrir WhatsApp | E7: @alaska_jeans | F7: Ver loja
A8: 6 | B8: ALASKA ATACADO | C8: Moda Feminina | D8: Abrir WhatsApp | E8: @alaskaatacado | F8: Ver loja
A9: 7 | B9: ALEIDA MODAS | C9: Moda Feminina | D9: Abrir WhatsApp | E9: @alaidamodastricos | F9: Ver loja
A10: 8 | B10: ALEX WINSTON | C10: Moda Feminina | D10: Abrir WhatsApp | E10: @alexis_wmodas | F10: Ver loja
A11: 9 | B11: ALL KISS STORE | C11: Moda Feminina | D11: Abrir WhatsApp | E11: @allkiss.store | F11: Ver loja
A12: 10 | B12: AMING MODAS | C12: Moda Feminina | D12: Abrir WhatsApp | E12: @a.mingjeans | F12: Ver loja
A13: 11 | B13: AMING MODAS ATACADO E VAREJO | C13: Moda Jeans | D13: Abrir WhatsApp | E13: @a.mingjeans | F13: Ver loja
A14: 12 | B14: ANDREA & ALEXANDRE | C14: Moda Feminina | D14: Abrir WhatsApp | E14: @andreaealexandrastore | F14: Ver loja
... A46: 44 | B46: DONA JENAS PREMIUM DELUXE | C46: Moda Jeans | D46: Abrir WhatsApp | E46: @donajeans_atacado | F46: Ver loja
A47: 45 | B47: DONA SEREIA | C47: Variedades | D47: Abrir WhatsApp | F47: Ver loja
A48: 46 | B48: DRIMY FASHION | C48: Moda Feminina | D48: Abrir WhatsApp | E48: @drimy_fashions | F48: Ver loja
A49: 47 | B49: DROGARIA E PERFUMARIA | C49: Variedades | D49: Abrir WhatsApp | F49: Ver loja
A50: 48 | B50: EFRAIM MODAS PLUS SIZE | C50: Moda Feminina Plus Size | D50: Abrir WhatsApp | E50: @efraimmodasplus | F50: Ver loja
A51: 49 | B51: ELIBELLE MODAS | C51: Moda Feminina | D51: Abrir WhatsApp | E51: @elibelle.modas | F51: Ver loja
A52: 50 | B52: ELICA | C52: Moda Feminina | D52: Abrir WhatsApp | E52: @elica_495 | F52: Ver loja
A53: 51 | B53: ELSA RAMIRESS | C53: Moda Feminina | D53: Abrir WhatsApp | E53: @elsaramiress | F53: Ver loja
A54: 52 | B54: EMILY MODAS | C54: Moda Feminina Plus Size | D54: Abrir WhatsApp | E54: @emilyplussizee | F54: Ver loja
A55: 53 | B55: ESTAÇÃO BRASIL | C55: Moda Feminina | D55: Abrir WhatsApp | E55: @estacao_brasil_ | F55: Ver loja
A56: 54 | B56: ESTILO BLOGUEIRINHA | C56: Moda Feminina | D56: Abrir WhatsApp | E56: @estilo%20blogueirinhaa_ | F56: Ver loja
A57: 55 | B57: ETIQUETA ROSA | C57: Moda Feminina | D57: Abrir WhatsApp | E57: @loja%20etiquera%20rosa | F57: Ver loja
A58: 56 | B58: EXCLUSIVA JEANS | C58: Moda Jeans | D58: Abrir WhatsApp | E58: @exclusivajeans_ | F58: Ver loja
A59: 57 | B59: FLOR IS BELLA | C59: Moda Feminina | D59: Abrir WhatsApp | E59: @flor_is_bellastore | F59: Ver loja
A60: 58 | B60: FLOR VICTÓRIA | C60: Moda Feminina | D60: Abrir WhatsApp | E60: @florvictoria | F60: Ver loja
A61: 59 | B61: FOFA MODA | C61: Variedades | F61: Ver loja
A62: 60 | B62: GT KIDS | C62: Moda Infantil / Juvenil | D62: Abrir WhatsApp | E62: @gt.kids | F62: Ver loja
A63: 61 | B63: GURIA OUSADA | C63: Moda Feminina | D63: Abrir WhatsApp | E63: @guriaousada_bras | F63: Ver loja
A64: 62 | B64: H B FASHION | C64: Moda Feminina | D64: Abrir WhatsApp | E64: @hbfashion_oficial | F64: Ver loja
A65: 63 | B65: H CAT ATACADO | C65: Moda Feminina | D65: Abrir WhatsApp | E65: @hcat.atacado | F65: Ver loja
A66: 64 | B66: H&H MODAS | C66: Moda Feminina | D66: Abrir WhatsApp | E66: @hh_modas | F66: Ver loja
A67: 65 | B67: HAIDAR JAQUETAS | C67: Moda Feminina | D67: Abrir WhatsApp | E67: @haidar%20jaquetas | F67: Ver loja
A68: 66 | B68: HANDOU ZHANG | C68: Moda Feminina | D68: Abrir WhatsApp | E68: @handouzhang9 | F68: Ver loja
A69: 67 | B69: HELLEN | C69: Moda Feminina | D69: Abrir WhatsApp | E69: @hellen.modaas | F69: Ver loja
A70: 68 | B70: IF STORE MODA FEMININA | C70: Moda Feminina | D70: Abrir WhatsApp | E70: @ifstoretshirt | F70: Ver loja
A71: 69 | B71: INTRUSO ESTILO FEMININO | C71: Moda Feminina Plus Size | D71: Abrir WhatsApp | E71: @intrusomodas | F71: Ver loja
A72: 70 | B72: IVONE FERNANDES | C72: Moda Feminina | D72: Abrir WhatsApp | E72: @ivone.fernandes125_modas | F72: Ver loja
A73: 71 | B73: JIAMEI SAIAS | C73: Moda Feminina | D73: Abrir WhatsApp | E73: @jiamei.saias | F73: Ver loja
... A87: 85 | B87: KN-RUTHMELY | C87: Moda Feminina | D87: Abrir WhatsApp | E87: @ruthmely95 | F87: Ver loja
A88: 86 | B88: KZ JAQUETAS | C88: Moda Masculina | D88: Abrir WhatsApp | F88: Ver loja
A89: 87 | B89: LEAH MODAS | C89: Moda Feminina | D89: Abrir WhatsApp | E89: @leah%20modas | F89: Ver loja
A90: 88 | B90: LESLY | C90: Moda Feminina | D90: Abrir WhatsApp | E90: @lesly.modas | F90: Ver loja
A91: 89 | B91: LILI | C91: Moda Feminina | D91: Abrir WhatsApp | E91: @j.z_7552 | F91: Ver loja
A92: 90 | B92: LILI MODAS | C92: Moda Feminina | D92: Abrir WhatsApp | E92: @lili.modas_ | F92: Ver loja
A93: 91 | B93: LIO STORE JAQUETAS | C93: Moda Masculina | D93: Abrir WhatsApp | E93: @liostore_fashion | F93: Ver loja
A94: 92 | B94: LISIÊ | C94: Moda Feminina | D94: Abrir WhatsApp | E94: @uselisie_ | F94: Ver loja
A95: 93 | B95: LISY MODAS | C95: Moda Feminina | D95: Abrir WhatsApp | E95: @lisy%20modas | F95: Ver loja
A96: 94 | B96: LOJA MAX | C96: Moda Feminina | D96: Abrir WhatsApp | E96: @caninde110 | F96: Ver loja
A97: 95 | B97: LOOK PREMIUM | C97: Moda Feminina | D97: Abrir WhatsApp | E97: @lookpremiumatacado | F97: Ver loja
A98: 96 | B98: LUCY MODAS 2.0 | C98: Moda Feminina Plus Size | D98: Abrir WhatsApp | E98: @lucy_modas2.0 | F98: Ver loja
A99: 97 | B99: LUDY FASHION | C99: Moda Feminina | D99: Abrir WhatsApp | E99: @ludy_fashion1 | F99: Ver loja
A100: 98 | B100: LUIZA MODAS | C100: Moda Feminina | D100: Abrir WhatsApp | E100: @modas_luiza15 | F100: Ver loja
... A142: 140 | B142: O REI DAS EMBALAGENS | C142: Outros / Diversos | D142: Abrir WhatsApp | E142: @rei_embalagens | F142: Ver loja
A143: 141 | B143: OCULOS – MEIAS- TOUCAS – LUVAS ATACADO | C143: Relógios e Óculos | D143: Abrir WhatsApp | F143: Ver loja
A144: 142 | B144: OHANA CAFÉ | C144: Alimentação | F144: Ver loja
A145: 143 | B145: OI GATA | C145: Moda Feminina Plus Size | D145: Abrir WhatsApp | E145: @oigata_1 | F145: Ver loja
A146: 144 | B146: OURO ROSA | C146: Moda Feminina | D146: Abrir WhatsApp | E146: @ourorosa.oficial | F146: Ver loja
A147: 145 | B147: PUSH | C147: Moda Feminina | D147: Abrir WhatsApp | E147: @push.atacado | F147: Ver loja
A148: 146 | B148: R. ELLE STORE | C148: Moda Feminina | D148: Abrir WhatsApp | E148: @r.ellestore | F148: Ver loja
A149: 147 | B149: RAFAELA MODA INTIMA | C149: Moda Feminina | D149: Abrir WhatsApp | E149: @rafaela.modaintima | F149: Ver loja
A150: 148 | B150: RAFFLESIA STORE | C150: Moda Feminina | D150: Abrir WhatsApp | E150: @rafflesia_store | F150: Ver loja
A151: 149 | B151: RAVENNA T-SHIRT | C151: Moda Feminina | D151: Abrir WhatsApp | E151: @_ravenna_modas | F151: Ver loja
A152: 150 | B152: RAYANNE FASHION | C152: Moda Feminina | D152: Abrir WhatsApp | E152: @modarayannefashion | F152: Ver loja
A153: 151 | B153: RC7 FASHION ATACADO E VAREJO | C153: Moda Feminina | D153: Abrir WhatsApp | E153: @rc7fashion | F153: Ver loja
A154: 152 | B154: RC7 FASHION ATACADO E VAREJO | C154: Moda Feminina | D154: Abrir WhatsApp | E154: @rc7fashion | F154: Ver loja
A155: 153 | B155: REBECCA FREITAS GIRLS | C155: Moda Feminina Plus Size | D155: Abrir WhatsApp | E155: @rebeccafreitas_girls_plusise | F155: Ver loja
A156: 154 | B156: REFINADA | C156: Moda Feminina | D156: Abrir WhatsApp | E156: @reffinada | F156: Ver loja
A157: 155 | B157: REI DAS JAQUETAS | C157: Outros / Diversos | D157: Abrir WhatsApp | E157: @rei_das_jaquetas | F157: Ver loja
A158: 156 | B158: REI DO MATTE | C158: Alimentação | E158: @reidomate.caninde | F158: Ver loja
A159: 157 | B159: REI DO TRICOT | C159: Moda Feminina | D159: Abrir WhatsApp | E159: @reidotricot | F159: Ver loja
A160: 158 | B160: RENASCER | C160: Moda Feminina Plus Size | D160: Abrir WhatsApp | E160: @renascermodas7 | F160: Ver loja
A161: 159 | B161: RIMA CORES MODA FEMININA | C161: Moda Feminina | D161: Abrir WhatsApp | E161: @rimacores | F161: Ver loja
A162: 160 | B162: ROMANA | C162: Moda Feminina | D162: Abrir WhatsApp | E162: @romana._modas | F162: Ver loja
A163: 161 | B163: ROSA FINA | C163: Moda Feminina | D163: Abrir WhatsApp | E163: @rosafinaoficial | F163: Ver loja
A164: 162 | B164: ROSA LUA MODA FEMININA | C164: Moda Jeans | D164: Abrir WhatsApp | E164: @rosalua_atacado | F164: Ver loja
A165: 163 | B165: RUSSO MODAS | C165: Moda Feminina | D165: Abrir WhatsApp | E165: @russo_modas | F165: Ver loja
A166: 164 | B166: SKY MASSAGE | C166: Variedades | D166: Abrir WhatsApp | F166: Ver loja
A167: 165 | B167: SKYLER ACESSÓRIOS | C167: Acessórios e Bijuterias | D167: Abrir WhatsApp | E167: @skyler_acessorios | F167: Ver loja
A168: 166 | B168: SOFIA PERRIR | C168: Moda Feminina | D168: Abrir WhatsApp | E168: @sofia%20perrir | F168: Ver loja
A169: 167 | B169: SRJ MODA JEANS BY CONSCIÊNCIA | C169: Moda Jeans | D169: Abrir WhatsApp | E169: @srj_modajeans | F169: Ver loja
A170: 168 | B170: STEFANIE FRANCO | C170: Moda Feminina | D170: Abrir WhatsApp | E170: @stefaniefranco.oficial | F170: Ver loja
A171: 169 | B171: STEFANIE FRANCO | C171: Moda Feminina | D171: Abrir WhatsApp | E171: @stefaniefranco.oficial | F171: Ver loja
A172: 170 | B172: STELLA TRICOT | C172: Moda Feminina | D172: Abrir WhatsApp | E172: @stella_tricot | F172: Ver loja
A173: 171 | B173: SUELEN MODAS | C173: Moda Feminina | D173: Abrir WhatsApp | E173: @suelenmodas.oficial | F173: Ver loja
A174: 172 | B174: SUPER VAIDOSA | C174: Moda Feminina | D174: Abrir WhatsApp | E174: @supervaidosaatacado | F174: Ver loja
A175: 173 | B175: SVA | C175: Moda Fitness | D175: Abrir WhatsApp | E175: @supervaidosaactive | F175: Ver loja
A176: 174 | B176: SVA | C176: Moda Feminina | D176: Abrir WhatsApp | E176: @bi.bella | F176: Ver loja
A177: 175 | B177: UNIVERSO SACOLAS | C177: Outros / Diversos | D177: Abrir WhatsApp | E177: @universosacolas | F177: Ver loja
A178: 176 | B178: V AZEVEDO | C178: Moda Feminina | D178: Abrir WhatsApp | E178: @vazevedo.moda | F178: Ver loja
... A195: 193 | B195: YANE MODAS | C195: Moda Feminina | D195: Abrir WhatsApp | E195: @yane_modas_acessorios | F195: Ver loja

Sheet Porto Brás
A1: Shopping Porto Brás — 157 fornecedores mapeados
A2: Nº | B2: Loja / Fornecedor | C2: Categoria | D2: WhatsApp | E2: Instagram | F2: Site / Link | G2: Observação
A3: 1 | B3: A.K.D Moda Infantil E Adulto | C3: Moda Infantil / Juvenil | D3: Abrir WhatsApp | E3: @akd modas / vellamariamodasinfantil
A4: 2 | B4: Alan | C4: Moda Feminina | D4: Abrir WhatsApp | E4: @zhang663311
A5: 3 | B5: Ali Burguer | C5: Alimentação | D5: Abrir WhatsApp
A6: 4 | B6: Alto Stilo | C6: Moda Jeans | D6: Abrir WhatsApp | E6: @alto_stilo_imports
A7: 5 | B7: Amin Jeans | C7: Moda Jeans | D7: Abrir WhatsApp | E7: @amin_jeans
A8: 6 | B8: Ana Fashion | C8: Moda Feminina | D8: Abrir WhatsApp | E8: @ana.xiaofeng.liu
A9: 7 | B9: Antonio Agostinho Ribeiro | C9: Alimentação
A10: 8 | B10: Arco Íris Da Garoa | C10: Serviços Gerais | D10: Abrir WhatsApp | E10: @arcoirisdagaroa
A11: 9 | B11: Areen Plus | C11: Moda Feminina Plus Size | D11: Abrir WhatsApp | E11: @areenplus
A12: 10 | B12: Bamboo | C12: Moda Feminina | D12: Abrir WhatsApp | E12: @loja_bamboo
A13: 11 | B13: Bb Jeans | C13: Moda Jeans | E13: @b.b_jeans1
A14: 12 | B14: Bd Jeans | C14: Moda Jeans | D14: Abrir WhatsApp | E14: @bdjeans.sp
A15: 13 | B15: Bds Jeans Fashion | C15: Moda Jeans | D15: Abrir WhatsApp | E15: @marufabadin / neofashion-22
A16: 14 | B16: Bela Plus | C16: Moda Feminina Plus Size | D16: Abrir WhatsApp | E16: @belaplus.oficial
A17: 15 | B17: Bela Rosê Atacado | C17: Moda Feminina | E17: @bella_rose2017
A18: 16 | B18: Bijuterias Carmem | C18: Acessórios e Bijuterias | D18: Abrir WhatsApp | E18: @carmenbijuterias35
A19: 17 | B19: Blue Cherry Jeans | C19: Moda Jeans | D19: Abrir WhatsApp | E19: @Bluecherryjeans
A20: 18 | B20: Boneco Cobertores | C20: Decoração e Casa | E20: @bonecocobertores404
A21: 19 | B21: Box 319 / 320 | C21: Moda Feminina | D21: Abrir WhatsApp | E21: @calcamenina319
A22: 20 | B22: Box 374 / 375 – Óculos | C22: Relógios e Óculos | D22: Abrir WhatsApp
A23: 21 | B23: Box 53 | C23: Moda Praia | D23: Abrir WhatsApp | E23: @maria porto bras 53
A24: 22 | B24: Box 54 | C24: Moda Feminina | D24: Abrir WhatsApp | E24: @egligi / charlote_fashion99
A25: 23 | B25: Box 60 E 62 | C25: Moda Feminina | D25: Abrir WhatsApp | E25: @jennyxu815
A26: 24 | B26: Bruna Moda Feminina | C26: Moda Feminina | D26: Abrir WhatsApp | E26: @br.una8360
A27: 25 | B27: Byung Atacado Modas | C27: Moda Feminina | D27: Abrir WhatsApp
A28: 26 | B28: C Y-Sir | C28: Moda Feminina | D28: Abrir WhatsApp | E28: @ti.ng2895
A29: 27 | B29: Camila Alves Dos Santos | C29: Moda Feminina | E29: @puro_estiloelegante
A30: 28 | B30: Casa Das Embalagens | C30: Outros / Diversos | D30: Abrir WhatsApp | E30: @casadasembalagensbras
A31: 29 | B31: Cattleya | C31: Moda Jeans | D31: Abrir WhatsApp | E31: @cattleya_lojaofficial
A32: 30 | B32: Celina Modas | C32: Moda Feminina | D32: Abrir WhatsApp | E32: @celinamodafeminina189
A33: 31 | B33: Changchun Chen Me | C33: Moda Feminina | D33: Abrir WhatsApp | E33: @jin.2360
A34: 32 | B34: Chen Box 304 | C34: Moda Praia
A35: 33 | B35: Dan Moda | C35: Moda Feminina | D35: Abrir WhatsApp | E35: @danmoda.in
A36: 34 | B36: Dhaka Jeans | C36: Moda Jeans | D36: Abrir WhatsApp | E36: @dhakajeans_feminina
A37: 35 | B37: Dien | C37: Moda Feminina | D37: Abrir WhatsApp | E37: @dien.moda
A38: 36 | B38: Dong Dong | C38: Moda Feminina | D38: Abrir WhatsApp | E38: @martaportobras
A39: 37 | B39: Dykas Modinha | C39: Moda Feminina | D39: Abrir WhatsApp | E39: @delpiero_modinhas / kendric_modinhas
A40: 38 | B40: Eliana Confecções | C40: Moda Feminina | E40: @eliana_confeccoes_noemi
A41: 39 | B41: Elite Jeans | C41: Moda Jeans | E41: @elite_jeans
A42: 40 | B42: Erick Fashion | C42: Moda Feminina | D42: Abrir WhatsApp | E42: @zhangjunqiao89
A43: 41 | B43: Fa Jaquetas | C43: Moda Jeans | D43: Abrir WhatsApp
A44: 42 | B44: Felipe Box 302 | C44: Acessórios e Bijuterias | D44: Abrir WhatsApp | E44: @hengeletronicos
A45: 43 | B45: Fen Modas | C45: Moda Feminina | D45: Abrir WhatsApp | E45: @fmfashion_8
A46: 44 | B46: Feng | C46: Moda Feminina | D46: Abrir WhatsApp | E46: @fen1559
A47: 45 | B47: Ferchu Modas | C47: Moda Feminina | E47: @ferchumodas
A48: 46 | B48: Fernando & Piero Acessorios Ltda | C48: Acessórios e Bijuterias | D48: Abrir WhatsApp | E48: @fernando_piero_bijoux
A49: 47 | B49: G & R Modas | C49: Moda Feminina | D49: Abrir WhatsApp | E49: @modasger
A50: 48 | B50: Galaxy Classic | C50: Moda Feminina | D50: Abrir WhatsApp | E50: @galaxy.chenqingqing / normaesstelanf
A51: 49 | B51: Garra Da Gata | C51: Moda Feminina Plus Size | D51: Abrir WhatsApp | E51: @garradagata.portobras
A52: 50 | B52: Gaúchos Do Brás | C52: Alimentação
A53: 51 | B53: General Modas | C53: Moda Jeans | D53: Abrir WhatsApp | E53: @general.modas.sp / halawim36gmail.com
A54: 52 | B54: Got Fit Vestindo Guerreiras | C54: Moda Fitness | D54: Abrir WhatsApp | E54: @got_fit_oficial / belin_plus_vestindo_guerreiras
A55: 53 | B55: Graziela Gouveia Ferreira | C55: Moda Feminina | D55: Abrir WhatsApp | E55: @moniprado.moda
A56: 54 | B56: Hassan Modas | C56: Moda Jeans | D56: Abrir WhatsApp | E56: @ali_modas390
A57: 55 | B57: Hb Girls | C57: Moda Feminina | D57: Abrir WhatsApp | E57: @hboficial
A58: 56 | B58: Henrique Modas | C58: Moda Masculina | D58: Abrir WhatsApp | E58: @he.nrique1458
A59: 57 | B59: Hong Xing Da | C59: Moda Feminina | D59: Abrir WhatsApp | E59: @lin.3975 / LIN.39752
A60: 58 | B60: Hugo Adolfo Mamani Aruata | C60: Moda Feminina | D60: Abrir WhatsApp | E60: @qhanamodasoficial
A61: 59 | B61: Ines Quispe Pacheco | C61: Moda Feminina | D61: Abrir WhatsApp | E61: @modas_chely
A62: 60 | B62: Ingrid Bijux | C62: Acessórios e Bijuterias | D62: Abrir WhatsApp | E62: @bijuxingrid
A63: 61 | B63: Isa Kids | C63: Moda Infantil / Juvenil | D63: Abrir WhatsApp | E63: @I.S.A KIDS
A64: 62 | B64: Jackson Relógios | C64: Relógios e Óculos | D64: Abrir WhatsApp | E64: @jackson_relogios
A65: 63 | B65: Jl Baby | C65: Moda Infantil / Juvenil | D65: Abrir WhatsApp | E65: @j.lbaby2
A66: 64 | B66: Johana Confecções | C66: Moda Feminina | E66: @johanabylaura
A67: 65 | B67: Ka & Ke Modas | C67: Moda Feminina | E67: @Modas_ka_ke
A68: 66 | B68: Kadi International | C68: Moda Jeans | D68: Abrir WhatsApp | E68: @multipass_py
A69: 67 | B69: Kaka Xu | C69: Moda Masculina | D69: Abrir WhatsApp | E69: @kaka.xu
A70: 68 | B70: Kalil Assistência Técnica | C70: Acessórios e Bijuterias | E70: @kalilassistencia
A71: 69 | B71: Kelly Santos Moda | C71: Moda Feminina | D71: Abrir WhatsApp | E71: @Kellysantosmodas
A72: 70 | B72: Kendric Modas | C72: Moda Feminina | D72: Abrir WhatsApp | E72: @kendric_modinhas
A73: 71 | B73: Keum Yi Han | C73: Moda Feminina | D73: Abrir WhatsApp | E73: @Keum_718
A74: 72 | B74: Khalil Ibrahim Abou Abbas | C74: Acessórios e Bijuterias | E74: @reidaassistenciapage
A75: 73 | B75: Kids Line | C75: Moda Íntima
A76: 74 | B76: King Sail | C76: Moda Infantil / Juvenil | D76: Abrir WhatsApp
A77: 75 | B77: Kk Fashion | C77: Moda Feminina | D77: Abrir WhatsApp | E77: @kkfashionmodas.br
A78: 76 | B78: Kovid Jeans | C78: Moda Jeans | D78: Abrir WhatsApp | E78: @kovidjeans / coronajeans391
A79: 77 | B79: Lado Doce T-Shirt | C79: Moda Feminina | D79: Abrir WhatsApp | E79: @ladodocetshirt
A80: 78 | B80: Leo Ibbo | C80: Moda Masculina | D80: Abrir WhatsApp | E80: @1660_leo
A81: 79 | B81: Leo Modas | C81: Moda Feminina | D81: Abrir WhatsApp | E81: @zw_leo
A82: 80 | B82: Lin Lin Moda Feminina | C82: Moda Feminina | D82: Abrir WhatsApp | E82: @jkl591702273
A83: 81 | B83: Lina | C83: Moda Feminina | D83: Abrir WhatsApp | E83: @li.na210
A84: 82 | B84: Lina Loja 116 | C84: Moda Feminina | D84: Abrir WhatsApp | E84: @1606.lina / gmw_variedade
A85: 83 | B85: Lineth Colque Acosta | C85: Moda Feminina | D85: Abrir WhatsApp
A86: 84 | B86: Lingwey | C86: Moda Feminina | D86: Abrir WhatsApp | E86: @lingwey2
A87: 85 | B87: Linha A Confecções | C87: Moda Jeans | D87: Abrir WhatsApp | E87: @linha_aconfecções
A88: 86 | B88: Loja 09 – Linali | C88: Moda Feminina | D88: Abrir WhatsApp | E88: @linali924
A89: 87 | B89: Loja 108 | C89: Moda Íntima | D89: Abrir WhatsApp
A90: 88 | B90: Loja 24 | C90: Moda Íntima | D90: Abrir WhatsApp | E90: @xiulanc54
A91: 89 | B91: Loja 4 – Lin | C91: Moda Feminina | D91: Abrir WhatsApp | E91: @LIN.3975 / LIN.39752
A92: 90 | B92: Loja 55 | C92: Moda Feminina | D92: Abrir WhatsApp | E92: @a2479682388
A93: 91 | B93: Loja Fofo | C93: Moda Feminina | D93: Abrir WhatsApp | E93: @loja_fofo
A94: 92 | B94: Loja Yang | C94: Moda Feminina | D94: Abrir WhatsApp | E94: @loja_yang_123
A95: 93 | B95: Lolita Modas | C95: Moda Feminina | D95: Abrir WhatsApp | E95: @lolitaroupa
A96: 94 | B96: Lorena Moda | C96: Moda Feminina | D96: Abrir WhatsApp | E96: @xj_moda / ay_moda_feminina
A97: 95 | B97: Marciano De Paula Branquinho Me | C97: Moda Masculina | D97: Abrir WhatsApp | E97: @malvoncamisaria
A98: 96 | B98: Margot Maqque Ttito | C98: Moda Feminina | E98: @raul_dobrassp
A99: 97 | B99: Maxtill Eletrônico | C99: Acessórios e Bijuterias | D99: Abrir WhatsApp | E99: @exxuma_eletronicos2019
A100: 98 | B100: Mc Donald’s | C100: Alimentação
...

Sheet All Brás
A1: Shopping All Brás — 105 fornecedores mapeados
A2: Nº | B2: Loja / Fornecedor | C2: Categoria | D2: WhatsApp | E2: Instagram | F2: Site / Link | G2: Observação
A3: 1 | B3: ABIGAIL HAULEY MODAS | C3: Moda Feminina | D3: Abrir WhatsApp | E3: @abigailmodas8 | G3: Loja 1069
A4: 2 | B4: ADRI CONFECÇÕES | C4: Moda Feminina Plus Size | D4: Abrir WhatsApp | E4: @adri_confeccoes1055 | G4: Loja 1055
A5: 3 | B5: ALYAA MODAS | C5: Moda Feminina | D5: Abrir WhatsApp | E5: @aliaamodas | G5: Loja 1088
A6: 4 | B6: AY | C6: Moda Feminina Plus Size | D6: Abrir WhatsApp | E6: @celina.ayala.3139 | G6: Loja 1043
A7: 5 | B7: BENTA FLOR | C7: Moda Feminina | D7: Abrir WhatsApp | E7: @benta_flor | G7: Loja 1053
A8: 6 | B8: BETO CONFECÇÕES | C8: Moda Feminina Plus Size | D8: Abrir WhatsApp | E8: @mary_i_s_r | G8: Loja 1027
A9: 7 | B9: BRITANNY FASHION | C9: Moda Feminina | D9: Abrir WhatsApp | E9: @brittany_fashion_plus_size | G9: Loja 1120
A10: 8 | B10: C . TAMARA CONFECÇÕES | C10: Moda Feminina | D10: Abrir WhatsApp | E10: @c.tamaramodas | G10: Loja 1139
A11: 9 | B11: CHEEKY COFECÇÕES | C11: Moda Feminina Plus Size | D11: Abrir WhatsApp | G11: Loja 1091
A12: 10 | B12: CONFECÇOES GABRIELA | C12: Moda Feminina | D12: Abrir WhatsApp | E12: @confeccoes.gabriela | G12: Loja 1107-A
A13: 11 | B13: CONFECÇOES JKM | C13: Moda Feminina | D13: Abrir WhatsApp | E13: @tania.marca.12 | G13: Loja 1056
A14: 12 | B14: CONFECÇÕES ARIAS | C14: Moda Feminina Plus Size | D14: Abrir WhatsApp | E14: @moda_arias | G14: Loja 1052
A15: 13 | B15: CONFECÇÕES CARMEN | C15: Moda Feminina | D15: Abrir WhatsApp | E15: @carmen_confeccoes | G15: Loja 1118
A16: 14 | B16: CONFECÇÕES CELESTE | C16: Moda Feminina | D16: Abrir WhatsApp | E16: @confeccoes_celeste | G16: Loja 1106
A17: 15 | B17: CONFECÇÕES DAISO-GIJO | C17: Moda Feminina | D17: Abrir WhatsApp | E17: @daisa_gijo | G17: Loja 1054
A18: 16 | B18: CONFECÇÕES DAMARIS | C18: Moda Feminina | D18: Abrir WhatsApp | E18: @plusdamaris | G18: Loja 1099
A19: 17 | B19: CONFECÇÕES F.L | C19: Moda Feminina | D19: Abrir WhatsApp | E19: @flconfeccoess | G19: Loja 1137
A20: 18 | B20: CONFECÇÕES FLORESNAT | C20: Moda Feminina Plus Size | D20: Abrir WhatsApp | E20: @floresnatatacado | G20: Loja 1046
A21: 19 | B21: CONFECÇÕES FLOWERS | C21: Moda Feminina Plus Size | D21: Abrir WhatsApp | E21: @abigailmodas8 | G21: Loja 1071
A22: 20 | B22: CONFECÇÕES GABRIELA | C22: Moda Feminina Plus Size | D22: Abrir WhatsApp | E22: @confeccoes.gabriela | G22: Loja 1107A
A23: 21 | B23: CONFECÇÕES KETAL | C23: Moda Feminina Plus Size | D23: Abrir WhatsApp | G23: Loja 1087
A24: 22 | B24: CONFECÇÕES LUIS | C24: Moda Feminina | D24: Abrir WhatsApp | E24: @confeccoes_luis | G24: Loja 1026
A25: 23 | B25: CONFECÇÕES LUIS | C25: Moda Feminina | D25: Abrir WhatsApp | G25: Loja 1094
A26: 24 | B26: CONFECÇÕES MELISSA | C26: Moda Feminina | D26: Abrir WhatsApp | G26: Loja 1057
A27: 25 | B27: CONFECÇÕES MOISES | C27: Moda Feminina Plus Size | D27: Abrir WhatsApp | E27: @confeciones_moises | G27: Loja 1132
A28: 26 | B28: CONFECÇÕES SANGA | C28: Moda Feminina Plus Size | D28: Abrir WhatsApp | E28: @confeccoes_sanga | G28: Loja 1063
A29: 27 | B29: CONFECÇÕES SML | C29: Moda Feminina Plus Size | D29: Abrir WhatsApp | E29: @samuelyquisi | G29: Loja 1050
A30: 28 | B30: DANIELA ARTESANATOS | C30: Acessórios e Bijuterias | D30: Abrir WhatsApp | E30: @daniela_artesanatos | G30: Loja 1278
A31: 29 | B31: DEEVANI CONFECÇÕES | C31: Moda Feminina | D31: Abrir WhatsApp | E31: @deevaniconfecções | G31: Loja 1147
A32: 30 | B32: DENNNER CONFECÇÕES | C32: Moda Feminina | D32: Abrir WhatsApp | E32: @denner.modas | G32: Loja 1100
A33: 31 | B33: DIVAN LANCHES E PASTEIS | C33: Alimentação | D33: Abrir WhatsApp | G33: Loja 1335
A34: 32 | B34: ELVIA CONFECÇÕES | C34: Moda Feminina Plus Size | D34: Abrir WhatsApp | E34: @elvia_confeccoes | G34: Loja 1067
A35: 33 | B35: ESCALANTE | C35: Acessórios e Bijuterias | D35: Abrir WhatsApp | E35: @escalantebijoux | G35: Loja 1079
A36: 34 | B36: ESCALANTE BIJOUX | C36: Acessórios e Bijuterias | D36: Abrir WhatsApp | E36: @escalantebijoux | G36: Loja 1108
A37: 35 | B37: EXCLUSIVA BELA | C37: Moda Feminina Plus Size | D37: Abrir WhatsApp | E37: @exclusivabella_plus | G37: Loja 1104
A38: 36 | B38: FARID-E MODAS | C38: Moda Feminina Plus Size | D38: Abrir WhatsApp | E38: @fari_dmodas | G38: Loja 1133
A39: 37 | B39: FARMÁCIA POUPE MAIS | C39: Serviços Gerais | D39: Abrir WhatsApp | E39: @poupemaisdrogarias | G39: Loja 1005
A40: 38 | B40: FINA FLOR | C40: Moda Feminina | D40: Abrir WhatsApp | E40: @finaflor_outlet | G40: Loja 1119
A41: 39 | B41: G.ROSMERY | C41: Moda Feminina Plus Size | D41: Abrir WhatsApp | E41: @rosemary.modas12 | G41: Loja 1058
A42: 40 | B42: G2G POST EXPRESS | C42: Serviços Gerais | D42: Abrir WhatsApp | E42: @g2gpostexpress | G42: Loja 1144
A43: 41 | B43: GAUCHO RESTAURANTES | C43: Alimentação | G43: Loja 1332
A44: 42 | B44: GIRAFFAS | C44: Alimentação | D44: Abrir WhatsApp | E44: @redegiraffas | G44: Loja 1334
A45: 43 | B45: HSA KEBABE | C45: Alimentação | D45: Abrir WhatsApp | E45: @hsa_kebabe | G45: Loja 1001
A46: 44 | B46: IMPERIAL RESTAURANTES | C46: Alimentação | G46: Loja 1333
A47: 45 | B47: IS ISA MODAS | C47: Moda Feminina Plus Size | D47: Abrir WhatsApp | E47: @issa.modas | G47: Loja 1128
A48: 46 | B48: J.C CONFECÇÕES | C48: Moda Feminina | D48: Abrir WhatsApp | E48: @jcfeminix | G48: Loja 1078
A49: 47 | B49: JADEFASHION | C49: Moda Feminina Plus Size | D49: Abrir WhatsApp | E49: @jadefashionplusszise | G49: Loja 1140
A50: 48 | B50: JHONAS CONFECÇÕES | C50: Moda Feminina Plus Size | D50: Abrir WhatsApp | E50: @jhonas_confeccoes | G50: Loja 1065
A51: 49 | B51: JHURY MODAS | C51: Moda Feminina Plus Size | D51: Abrir WhatsApp | E51: @jhury_modasplus | G51: Loja 1022
A52: 50 | B52: JIREH | C52: Moda Feminina Plus Size | D52: Abrir WhatsApp | E52: @jirehplussize | G52: Loja 1044
A53: 51 | B53: JKL MODAS | C53: Moda Feminina Plus Size | D53: Abrir WhatsApp | E53: @jklmodaplussize | G53: Loja 1061
A54: 52 | B54: JULY PLUS | C54: Moda Feminina Plus Size | D54: Abrir WhatsApp | E54: @julymodas8 | G54: Loja 1109
A55: 53 | B55: JYEZ MODAS | C55: Moda Feminina Plus Size | D55: Abrir WhatsApp | G55: Loja 1145
A56: 54 | B56: KIARA MODAS | C56: Moda Feminina Plus Size | D56: Abrir WhatsApp | E56: @kiara.modass | G56: Loja 1073
A57: 55 | B57: L.C.D CONFECÇÕES | C57: Moda Feminina | D57: Abrir WhatsApp | G57: Loja 1066
A58: 56 | B58: LAURA CONFECÇÕES | C58: Moda Feminina Plus Size | D58: Abrir WhatsApp | G58: Loja 1077
A59: 57 | B59: LIYAA MODAS | C59: Moda Feminina Plus Size | D59: Abrir WhatsApp | G59: Loja 1075
A60: 58 | B60: LOJA 1102 | C60: Moda Feminina | D60: Abrir WhatsApp | G60: Loja 1102
A61: 59 | B61: LUDAI CONFECÇÃO | C61: Moda Feminina | D61: Abrir WhatsApp | E61: @ludai_modas | G61: Loja 1038
A62: 60 | B62: M & M MODAS | C62: Moda Feminina Plus Size | D62: Abrir WhatsApp | E62: @mamanimodas | G62: Loja 1115
A63: 61 | B63: M&R MATHEUS & ROGER | C63: Moda Masculina | D63: Abrir WhatsApp | E63: @mrmodacamuflada | G63: Loja 1047
A64: 62 | B64: MAMA SO | C64: Alimentação | D64: Abrir WhatsApp | G64: Loja 1000
A65: 63 | B65: MATEUS CONFECÇÕES | C65: Moda Feminina Plus Size | D65: Abrir WhatsApp | E65: @marcelaaruquipa | G65: Loja 1114
A66: 64 | B66: MAYTE MODAS | C66: Moda Feminina Plus Size | D66: Abrir WhatsApp | E66: @mayte_modas_plus_size | G66: Loja 1136
A67: 65 | B67: MC ALEJO CONFECÇÕES | C67: Moda Feminina | D67: Abrir WhatsApp | E67: @mc.alejoconfeccoes | G67: Loja 1093
A68: 66 | B68: MERCY | C68: Moda Feminina | D68: Abrir WhatsApp | E68: @mercymodas_ | G68: Loja 1036
A69: 67 | B69: MILKA ESTER | C69: Moda Feminina | D69: Abrir WhatsApp | E69: @milkaestermoda | G69: Loja 1037
A70: 68 | B70: MILKA ESTER | C70: Moda Feminina | D70: Abrir WhatsApp | E70: @milkaestermoda | G70: Loja 1072
A71: 69 | B71: MODAS AMASHA | C71: Moda Feminina Plus Size | D71: Abrir WhatsApp | E71: @modas_amasha | G71: Loja 1024
A72: 70 | B72: MODAS DARIA | C72: Moda Feminina Plus Size | D72: Abrir WhatsApp | E72: @modas_daria | G72: Loja 1131
A73: 71 | B73: MODAS FRAN Y MARY | C73: Moda Feminina | D73: Abrir WhatsApp | E73: @franmary_plussize_modas | G73: Loja 1082
A74: 72 | B74: MODAS PAOLA | C74: Moda Festa | D74: Abrir WhatsApp | E74: @modaspaola86 | G74: Loja 1025
A75: 73 | B75: MODAS SILVIA | C75: Moda Feminina Plus Size | D75: Abrir WhatsApp | E75: @modas_silvia2 | G75: Loja 1040
A76: 74 | B76: MODAS YAVE | C76: Moda Feminina Plus Size | D76: Abrir WhatsApp | E76: @modasyave | G76: Loja 1045
A77: 75 | B77: MODAS YELUZ | C77: Moda Feminina | D77: Abrir WhatsApp | G77: Loja 1030
A78: 76 | B78: NATHALI | C78: Moda Feminina Plus Size | D78: Abrir WhatsApp | E78: @nathalimodas | G78: Loja 1105
A79: 77 | B79: NEW BELEZA MODAS | C79: Moda Feminina | D79: Abrir WhatsApp | E79: @newbelezamodas | G79: Loja 1121
A80: 78 | B80: NEW ELLEGANCY COLLECTION | C80: Moda Feminina | D80: Abrir WhatsApp | E80: @newellegancycollection | G80: Loja 1111
A81: 79 | B81: ONLOG | C81: Serviços Gerais | D81: Abrir WhatsApp | E81: @onlogenvios | G81: Loja 1006
A82: 80 | B82: PALÁCIO DAS CRIANÇAS | C82: Moda Infantil / Juvenil | D82: Abrir WhatsApp | E82: @palacio_das_criancas | G82: Loja 1009
A83: 81 | B83: PATTY MODAS | C83: Moda Feminina | D83: Abrir WhatsApp | E83: @modaspatty68 | G83: Loja 1039
A84: 82 | B84: REBEKA PLUS SIZE | C84: Moda Feminina | D84: Abrir WhatsApp | E84: @rebaka_plussize | G84: Loja 1149
A85: 83 | B85: RINA CONFECÇÕES | C85: Moda Feminina Plus Size | D85: Abrir WhatsApp | E85: @rina_confecções_ | G85: Loja 1117
A86: 84 | B86: SAMILIA | C86: Moda Feminina | D86: Abrir WhatsApp | E86: @f26samlia_fashion | G86: Loja 1035
A87: 85 | B87: SANGA CONFECÇÕES | C87: Moda Feminina | D87: Abrir WhatsApp | E87: @confeccoes_sanga | G87: Loja 1034
A88: 86 | B88: SARA MODAS | C88: Moda Feminina Plus Size | D88: Abrir WhatsApp | E88: @sara_modas_ | G88: Loja 1041
A89: 87 | B89: SELYM MODAS | C89: Moda Feminina | D89: Abrir WhatsApp | E89: @modaselym | G89: Loja 1083
A90: 88 | B90: SHEYLA MODAS | C90: Moda Feminina Plus Size | D90: Abrir WhatsApp | E90: @sheyla-modas2 | G90: Loja 1042
A91: 89 | B91: SIENA CONFECÇÕES | C91: Moda Feminina | D91: Abrir WhatsApp | G91: Loja 1060
A92: 90 | B92: SLENA CONFECÇÕES | C92: Moda Feminina | D92: Abrir WhatsApp | E92: @slenaconfecções | G92: Loja 1101
A93: 91 | B93: SOE NAYARA | C93: Moda Feminina | D93: Abrir WhatsApp | E93: @soe_nayara | G93: Loja 1033
A94: 92 | B94: SS JEANS | C94: Moda Jeans | D94: Abrir WhatsApp | E94: @ssjeans_ | G94: Loja 1008
A95: 93 | B95: TAPIOCA DO PESSOA | C95: Alimentação | D95: Abrir WhatsApp | E95: @tapiocadopessoa | G95: Loja 1336
A96: 94 | B96: TATI MODAS | C96: Moda Feminina Plus Size | D96: Abrir WhatsApp | E96: @tati_modas.sp | G96: Loja 1134
A97: 95 | B97: TROPICAL COLOR | C97: Moda Feminina Plus Size | D97: Abrir WhatsApp | G97: Loja 1086
A98: 96 | B98: UMAI | C98: Alimentação | D98: Abrir WhatsApp | E98: @restauranteumai | G98: Loja 1002
A99: 97 | B99: VERO CONFECÇÕES | C99: Moda Feminina Plus Size | D99: Abrir WhatsApp | E99: @vero_confeccoes | G99: Loja 1112
A100: 98 | B100: VILLA NUEVA | C100: Moda Feminina Plus Size | D100: Abrir WhatsApp | E100: @villanueva_confeccoes | G100: Loja 1051
...

Sheet O Melhor do Brás
A1: O Melhor do Brás (Diretório) — 22 fornecedores mapeados
A2: Nº | B2: Loja / Fornecedor | C2: Categoria | D2: WhatsApp | E2: Instagram | F2: Site / Link | G2: Observação
A3: 1 | B3: ARTCOM VIDROS | C3: Embalagens, Expositores e Manequins | E3: @artcomvidros | F3: Ver loja
A4: 2 | B4: BB VINDO | C4: Moda Infantil / Juvenil | E4: @bb_vindo_oficial | F4: Ver loja
A5: 3 | B5: BRUNFER JEANS | C5: Moda Feminina Plus Size | E5: @brunferjeans | F5: Ver loja
A6: 4 | B6: CASA DAS ARARAS | C6: Embalagens, Expositores e Manequins | E6: @casadasararas | F6: Ver loja
A7: 5 | B7: COMFORTECH | C7: Decoração e Casa | E7: @comfortechbr | F7: Ver loja
A8: 6 | B8: CROCKER JEANS | C8: Moda Jeans | E8: @crocker_jeans | F8: Ver loja
A9: 7 | B9: GOL TÊXTIL | C9: Tecidos e Retalhos | E9: @goltextil_ | F9: Ver loja
A10: 8 | B10: LA SÈVE | C10: Moda Feminina Plus Size | E10: @la_seve_modafeminina | F10: Ver loja
A11: 9 | B11: LOJA CAROLINA BABY | C11: Moda Infantil / Juvenil | F11: Ver loja
A12: 10 | B12: LUMINI JEANS | C12: Moda Jeans | E12: @luminijeans | F12: Ver loja
A13: 11 | B13: LÍQUIDO OUTLET | C13: Moda Fitness | E13: @?hl=pt | F13: Ver loja
A14: 12 | B14: MANI'S CABIDES | C14: Embalagens, Expositores e Manequins | E14: @maniscabidesoficial | F14: Ver loja
A15: 13 | B15: MARIA ALICE MODAS - Plus Size | C15: Moda Feminina Plus Size | E15: @mariaalicemoda757 | F15: Ver loja
A16: 14 | B16: MODA MAZAL - Plus Size | C16: Moda Feminina Plus Size | E16: @moda_mazal | F16: Ver loja
A17: 15 | B17: NEWMAX CONFECÇÕES | C17: Moda Jeans | E17: @confeccoesnewmaxltda | F17: Ver loja
A18: 16 | B18: NIPO CENTER | C18: Moda Festa | E18: @nipocenter | F18: Ver loja
A19: 17 | B19: SHOPPING MEGA POLO MODA | C19: Outros / Diversos | E19: @megapolomoda | F19: Ver loja
A20: 18 | B20: SNAPPER | C20: Moda Masculina | E20: @snapper.co | F20: Ver loja
A21: 19 | B21: STONE WALL | C21: Moda Masculina | E21: @stonewalllojaoficial | F21: Ver loja
A22: 20 | B22: THIPTON | C22: Moda Feminina | E22: @thipton_ | F22: Ver loja
A23: 21 | B23: TUTTO AMORE OFICIAL | C23: Moda Feminina | E23: @tuttoamoreoficial | F23: Ver loja
A24: 22 | B24: UNIBES BAZAR | C24: Moda Infantil / Juvenil | E24: @unibes | F24: Ver loja
